Workbook
Name UPDATE: 'Data Sheet'!$E$1

Sheet Data Sheet
A1: COMPANY NAME | B1: HINDUSTAN UNILEVER LTD | E1: =IF(B2<>B3, "A NEW VERSION OF THE WORKSHEET IS AVAILABLE", "")
A2: LATEST VERSION | B2: 2.1 | E2: PLEASE DO NOT MAKE ANY CHANGES TO THIS SHEET
A3: CURRENT VERSION | B3: 2.1
A5: META
A6: Number of shares | B6: =IF(B9>0, B9/B8, 0) -> 234.9591
A7: Face Value | B7: 1
A8: Current Price | B8: 1826.3
A9: Market Capitalization | B9: 429105.81
A15: PROFIT & LOSS
A16: Report Date | B16: 42825 | C16: 43190 | D16: 43555 | E16: 43921 | F16: 44286 | G16: 44651 | H16: 45016 | I16: 45382 | J16: 45747 | K16: 46112
A17: Sales | B17: 31890 | C17: 34525 | D17: 38224 | E17: 38785 | F17: 45996 | G17: 51193 | H17: 59144 | I17: 60469 | J17: 59676 | K17: 61975
A18: Raw Material Cost | B18: 13165 | C18: 13859 | D18: 15430 | E18: 15378 | F18: 19784 | G18: 22398 | H18: 28042 | I18: 26598 | J18: 26445 | K18: 28883
A19: Change in Inventory | B19: -156 | C19: 71 | D19: -12 | E19: 121 | F19: 391 | G19: 19 | H19: 53 | I19: 8 | J19: 78 | K19: 395
A20: Power and Fuel | B20: 257 | C20: 259 | D20: 269 | E20: 263 | F20: 304 | G20: 277 | H20: 325 | I20: 384 | J20: 341 | K20: 364
A21: Other Mfr. Exp | B21: 2771 | C21: 2958 | D21: 3018 | E21: 2860 | F21: 2847 | G21: 3329 | H21: 3705 | I21: 3293 | J21: 3508 | K21: 3079
A22: Employee Cost | B22: 1620 | C22: 1745 | D22: 1747 | E22: 1691 | F22: 2229 | G22: 2399 | H22: 2665 | I22: 2782 | J22: 2715 | K22: 2843
A23: Selling and admin | B23: 6508 | C23: 7105 | D23: 7645 | E23: 7523 | F23: 7783 | G23: 8046 | H23: 8674 | I23: 10562 | J23: 9815 | K23: 9964
A24: Other Expenses | B24: 1366 | C24: 1394 | D24: 1466 | E24: 1591 | F24: 2116 | G24: 2260 | H24: 2154 | I24: 2668 | J24: 2786 | K24: 2773
A25: Other Income | B25: 767 | C25: 507 | D25: 437 | E25: 536 | F25: 286 | G25: 359 | H25: 578 | I25: 884 | J25: 1632 | K25: 5572
A26: Depreciation | B26: 396 | C26: 478 | D26: 524 | E26: 938 | F26: 1012 | G26: 1025 | H26: 1030 | I26: 1097 | J26: 1122 | K26: 1186
A27: Interest | B27: 22 | C27: 20 | D27: 28 | E27: 106 | F27: 108 | G27: 98 | H27: 101 | I27: 302 | J27: 350 | K27: 363
... A31: Dividend Amount | B31: 3672 | C31: 4320 | D31: 4752 | E31: 5400 | F31: 9517.5 | G31: 7990 | H31: 9165 | I31: 9870 | J31: 12455 | K31: 9635
A32: EBITDA | B32: =SUM(B28,B27,B26) -> 6814 | C32: =SUM(C28,C27,C26) -> 7783 | D32: =SUM(D28,D27,D26) -> 9074 | E32: =SUM(E28,E27,E26) -> 10136 | F32: =SUM(F28,F27,F26) -> 11610 | G32: =SUM(G28,G27,G26) -> 12862 | H32: =SUM(H28,H27,H26) -> 14210 | I32: =SUM(I28,I27,I26) -> 15074 | ... K32: =SUM(K28,K27,K26) -> 20036
A33: EBIT | B33: =B28+B27 -> 6418 | C33: =C28+C27 -> 7305 | D33: =D28+D27 -> 8550 | E33: =E28+E27 -> 9198 | F33: =F28+F27 -> 10598 | G33: =G28+G27 -> 11837 | H33: =H28+H27 -> 13180 | I33: =I28+I27 -> 13977 | ... K33: =K28+K27 -> 18850
A40: Quarters
A41: Report Date | B41: 45382 | C41: 45473 | D41: 45565 | E41: 45657 | F41: 45747 | G41: 45838 | H41: 45930 | I41: 46022 | J41: 46112 | K41: 46203
A42: Sales | B42: 14857 | C42: 15339 | D42: 15508 | E42: 15146 | F42: 14734 | G42: 15174 | H42: 15263 | I42: 15805 | J42: 15733 | K42: 16657
A43: Expenses | B43: 11422 | C43: 11733 | D43: 11861 | E43: 11582 | F43: 11268 | G43: 11694 | H43: 11644 | I43: 12165 | J43: 12008 | K43: 12889
A44: Other Income | B44: 203 | C44: 209 | D44: 293 | E44: 814 | F44: 254 | G44: 149 | H44: 350 | I44: 4594 | J44: 479 | K44: 158
A45: Depreciation | B45: 289 | C45: 298 | D45: 305 | E45: 285 | F45: 284 | G45: 289 | H45: 288 | I45: 299 | J45: 310 | K45: 314
A46: Interest | B46: 102 | C46: 85 | D46: 99 | E46: 102 | F46: 72 | G46: 105 | H46: 106 | I46: 84 | J46: 68 | K46: 64
A47: Profit before tax | B47: 3247 | C47: 3432 | D47: 3536 | E47: 3991 | F47: 3364 | G47: 3235 | H47: 3575 | I47: 7851 | J47: 3826 | K47: 3548
A48: Tax | B48: 841 | C48: 894 | D48: 924 | E48: 990 | F48: 871 | G48: 503 | H48: 885 | I48: 776 | J48: 896 | K48: 917
A49: Net profit | B49: 2406 | C49: 2538 | D49: 2612 | E49: 3001 | F49: 2493 | G49: 2732 | H49: 2690 | I49: 7075 | J49: 2930 | K49: 2631
A50: Operating Profit | B50: 3435 | C50: 3606 | D50: 3647 | E50: 3564 | F50: 3466 | G50: 3480 | H50: 3619 | I50: 3640 | J50: 3725 | K50: 3768
A55: BALANCE SHEET
A56: Report Date | B56: 42825 | C56: 43190 | D56: 43555 | E56: 43921 | F56: 44286 | G56: 44651 | H56: 45016 | I56: 45382 | J56: 45747 | K56: 46112
A57: Equity Share Capital | B57: 216 | C57: 216 | D57: 216 | E57: 216 | F57: 235 | G57: 235 | H57: 235 | I57: 235 | J57: 235 | K57: 235
A58: Reserves | B58: 6274 | C58: 6859 | D58: 7443 | E58: 7815 | F58: 47199 | G58: 48525 | H58: 49986 | I58: 50738 | J58: 48918 | K58: 48988
A59: Borrowings | F59: 943 | G59: 971 | H59: 1039 | I59: 1374 | J59: 1537 | K59: 1325
A60: Other Liabilities | B60: 8261 | C60: 10074 | D60: 10206 | E60: 11571 | F60: 19739 | G60: 20006 | H60: 20565 | I60: 24729 | J60: 27623 | K60: 27434
A61: Total | B61: 14751 | C61: 17149 | D61: 17865 | E61: 19602 | F61: 68116 | G61: 69737 | H61: 71825 | I61: 77076 | J61: 78313 | K61: 77982
A62: Net Block | B62: 4024 | C62: 4142 | D62: 4343 | E62: 5056 | F62: 51027 | G62: 51034 | H62: 51405 | I62: 52379 | J62: 52907 | K62: 52419
A63: Capital Work in Progress | B63: 203 | C63: 430 | D63: 373 | E63: 513 | F63: 623 | G63: 901 | H63: 1020 | I63: 915 | J63: 956 | K63: 833
A64: Investments | B64: 3779 | C64: 3111 | D64: 2949 | E64: 1500 | F64: 2995 | G64: 4122 | H64: 3794 | I64: 5493 | J64: 4602 | K64: 8879
A65: Other Assets | B65: 6745 | C65: 9466 | D65: 10200 | E65: 12533 | F65: 13471 | G65: 13680 | H65: 15606 | I65: 18289 | J65: 19848 | K65: 15851
A66: Total | B66: 14751 | C66: 17149 | D66: 17865 | E66: 19602 | F66: 68116 | G66: 69737 | H66: 71825 | I66: 77076 | J66: 78313 | K66: 77982
A67: Receivables | B67: 928 | C67: 1147 | D67: 1673 | E67: 1046 | F67: 1648 | G67: 1932 | H67: 2735 | I67: 2690 | J67: 3450 | K67: 3037
A68: Inventory | B68: 2362 | C68: 2359 | D68: 2422 | E68: 2636 | F68: 3383 | G68: 3890 | H68: 4031 | I68: 3812 | J68: 4161 | K68: 4383
A69: Cash & Bank | B69: 1671 | C69: 3373 | D69: 3688 | E69: 5017 | F69: 4321 | G69: 3618 | H69: 4422 | I69: 7216 | J69: 7293 | K69: 2830
A70: No. of Equity Shares | B70: 2164349639 | C70: 2164704405 | D70: 2164704405 | E70: 2164704405 | F70: 2349567819 | G70: 2349591262 | H70: 2349591262 | I70: 2349591262 | J70: 2349591262 | K70: 2349591262
A71: New Bonus Shares
A72: Face value | B72: 1 | C72: 1 | D72: 1 | E72: 1 | F72: 1 | G72: 1 | H72: 1 | I72: 1 | J72: 1 | K72: 1
A74: Other Assests | B74: =B65-SUM(B67:B69) -> 1784 | C74: =C65-SUM(C67:C69) -> 2587 | D74: =D65-SUM(D67:D69) -> 2417 | E74: =E65-SUM(E67:E69) -> 3834 | F74: =F65-SUM(F67:F69) -> 4119 | G74: =G65-SUM(G67:G69) -> 4240 | H74: =H65-SUM(H67:H69) -> 4418 | I74: =I65-SUM(I67:I69) -> 4571 | ... K74: =K65-SUM(K67:K69) -> 5601
A80: CASH FLOW:
A81: Report Date | B81: 42825 | C81: 43190 | D81: 43555 | E81: 43921 | F81: 44286 | G81: 44651 | H81: 45016 | I81: 45382 | J81: 45747 | K81: 46112
A82: Cash from Operating Activity | B82: 4953 | C82: 5913 | D82: 5728 | E82: 7305 | F82: 8957 | G82: 8964 | H82: 9626 | I82: 14884 | J82: 11606 | K82: 10496
A83: Cash from Investing Activity | B83: -752 | C83: -1261 | D83: -264 | E83: 1926 | F83: -1067 | G83: -1732 | H83: -1062 | I83: -4971 | J83: 6763 | K83: -3473
A84: Cash from Financing Activity | B84: -4264 | C84: -4651 | D84: -5462 | E84: -6676 | F84: -9280 | G84: -7984 | H84: -8966 | I84: -9890 | J84: -13031 | K84: -10684
A85: Net Cash Flow | B85: -63 | C85: 1 | D85: 2 | E85: 2555 | F85: -1390 | G85: -752 | H85: -402 | I85: 23 | J85: 5338 | K85: -3661
A90: PRICE: | B90: 872.61 | C90: 1276.11 | D90: 1633.53 | E90: 2199.83 | F90: 2327.12 | G90: 1960.7 | H90: 2450.44 | I90: 2167.14 | J90: 2161.88 | K90: 2055.2
A92: DERIVED:
A93: Adjusted Equity Shares in Cr | B93: 216.43 | C93: 216.45 | D93: 216.47 | E93: 216.48 | F93: 234.96 | G93: 234.96 | H93: 234.96 | I93: 234.96 | J93: 234.96 | K93: 234.96

Sheet Historical Financial Statement
B1: ="Historical Financial Statement for "&'Data Sheet'!B1 -> Historical Financial Statement for HINDUSTAN UNILEVER LTD
B2: ='Data Sheet'!A16 -> Report Date | C2: ='Data Sheet'!B16 -> 42825 | D2: ='Data Sheet'!C16 -> 43190 | E2: ='Data Sheet'!D16 -> 43555 | F2: ='Data Sheet'!E16 -> 43921 | G2: ='Data Sheet'!F16 -> 44286 | H2: ='Data Sheet'!G16 -> 44651 | I2: ='Data Sheet'!H16 -> 45016 | ... L2: ='Data Sheet'!K16 -> 46112 | M2: =L2+365 -> 46477 | N2: =M2+365 -> 46842 | O2: =N2+365 -> 47207 | P2: =O2+365 -> 47572 | Q2: =P2+365 -> 47937
M3: =L5*(1+0.07) -> 66313.25 | N3: =M5*(1+0.07) -> 74551.322 | O3: =N5*(1+0.07) -> 78581.333 | P3: =O5*(1+0.07) -> 82622.355 | Q3: =P5*(1+0.07) -> 86663.407 | R3: =_xlfn.RRI(15,C5,Q3) -> 0.068920524 | S3: =M3-L5 -> 4338.25 | T3: =N3-M3 -> 8238.0716 | U3: =O3-N3 -> 4030.0112 | V3: =P3-O3 -> 4041.0221 | W3: =Q3-P3 -> 4041.0523
A4: # | B4: Income Statement(in CR)
B5: ='Data Sheet'!A17 -> Sales | C5: ='Data Sheet'!B17 -> 31890 | D5: ='Data Sheet'!C17 -> 34525 | E5: ='Data Sheet'!D17 -> 38224 | F5: ='Data Sheet'!E17 -> 38785 | G5: ='Data Sheet'!F17 -> 45996 | H5: ='Data Sheet'!G17 -> 51193 | I5: ='Data Sheet'!H17 -> 59144 | ... L5: ='Data Sheet'!K17 -> 61975 | M5: =_xlfn.FORECAST.ETS(M$2,$C5:$L5,$C$2:$L$2) -> 69674.132 | N5: =_xlfn.FORECAST.ETS(N$2,$C5:$L5,$C$2:$L$2) -> 73440.498 | O5: =_xlfn.FORECAST.ETS(O$2,$C5:$L5,$C$2:$L$2) -> 77217.154 | P5: =_xlfn.FORECAST.ETS(P$2,$C5:$L5,$C$2:$L$2) -> 80993.839 | Q5: =_xlfn.FORECAST.ETS(Q$2,$C5:$L5,$C$2:$L$2) -> 84770.523 | R5: =(Q5/C5)^(1/15)-1 -> 0.067347956 | S5: =M5-L5 -> 7699.1323 | T5: =N5-M5 -> 3766.3656 | U5: =O5-N5 -> 3776.6562 | V5: =P5-O5 -> 3776.6844 | W5: =Q5-P5 -> 3776.6844
B6: Sales Growth In % | C6: =IFERROR((C5/B5)-1,(C5/C5)-1) -> 0 | D6: =IFERROR((D5/C5)-1,(D5/D5)-1) -> 0.082627783 | E6: =IFERROR((E5/D5)-1,(E5/E5)-1) -> 0.10713975 | F6: =IFERROR((F5/E5)-1,(F5/F5)-1) -> 0.014676643 | G6: =IFERROR((G5/F5)-1,(G5/G5)-1) -> 0.18592239 | H6: =IFERROR((H5/G5)-1,(H5/H5)-1) -> 0.11298809 | I6: =IFERROR((I5/H5)-1,(I5/I5)-1) -> 0.1553142 | J6: =IFERROR((J5/I5)-1,(J5/J5)-1) -> 0.022402949 | ... Q6: =IFERROR((Q5/P5)-1,(Q5/Q5)-1) -> 0.046629281
B7: COGS | C7: =SUM('Data Sheet'!B18,'Data Sheet'!B20:B22)-('Data Sheet'!B19) -> 17969 | D7: =SUM('Data Sheet'!C18,'Data Sheet'!C20:C22)-('Data Sheet'!C19) -> 18750 | E7: =SUM('Data Sheet'!D18,'Data Sheet'!D20:D22)-('Data Sheet'!D19) -> 20476 | F7: =SUM('Data Sheet'!E18,'Data Sheet'!E20:E22)-('Data Sheet'!E19) -> 20071 | G7: =SUM('Data Sheet'!F18,'Data Sheet'!F20:F22)-('Data Sheet'!F19) -> 24773 | H7: =SUM('Data Sheet'!G18,'Data Sheet'!G20:G22)-('Data Sheet'!G19) -> 28384 | I7: =SUM('Data Sheet'!H18,'Data Sheet'!H20:H22)-('Data Sheet'!H19) -> 34684 | J7: =SUM('Data Sheet'!I18,'Data Sheet'!I20:I22)-('Data Sheet'!I19) -> 33049 | ... L7: =SUM('Data Sheet'!K18,'Data Sheet'!K20:K22)-('Data Sheet'!K19) -> 34774 | M7: =Calculation!L5 -> 38311.555 | N7: =Calculation!M5 -> 40282.675 | O7: =Calculation!N5 -> 42396.074 | P7: =Calculation!O5 -> 44577.915 | Q7: =Calculation!P5 -> 46935.384
B8: Gross Profit | C8: =C5-C7 -> 13921 | D8: =D5-D7 -> 15775 | E8: =E5-E7 -> 17748 | F8: =F5-F7 -> 18714 | G8: =G5-G7 -> 21223 | H8: =H5-H7 -> 22809 | I8: =I5-I7 -> 24460 | J8: =J5-J7 -> 27420 | ... Q8: =Q5-Q7 -> 37835.139
B9: Gross Profit Margin | C9: =C8/C5 -> 0.43653183 | D9: =D8/D5 -> 0.45691528 | E9: =E8/E5 -> 0.46431561 | F9: =F8/F5 -> 0.48250612 | G9: =G8/G5 -> 0.46140969 | H9: =H8/H5 -> 0.4455492 | I9: =I8/I5 -> 0.41356689 | J9: =J8/J5 -> 0.45345549 | ... Q9: =Q8/Q5 -> 0.44632424
B11: ='Data Sheet'!A23 -> Selling and admin | C11: ='Data Sheet'!B23 -> 6508 | D11: ='Data Sheet'!C23 -> 7105 | E11: ='Data Sheet'!D23 -> 7645 | F11: ='Data Sheet'!E23 -> 7523 | G11: ='Data Sheet'!F23 -> 7783 | H11: ='Data Sheet'!G23 -> 8046 | I11: ='Data Sheet'!H23 -> 8674 | ... L11: ='Data Sheet'!K23 -> 9964 | M11: =Calculation!L9 -> 11298.279 | N11: =Calculation!M9 -> 11822.718 | O11: =Calculation!N9 -> 12479.779 | P11: =Calculation!O9 -> 13292.112 | Q11: =Calculation!P9 -> 13762.782
B12: ='Data Sheet'!A24 -> Other Expenses | C12: ='Data Sheet'!B24 -> 1366 | D12: ='Data Sheet'!C24 -> 1394 | E12: ='Data Sheet'!D24 -> 1466 | F12: ='Data Sheet'!E24 -> 1591 | G12: ='Data Sheet'!F24 -> 2116 | H12: ='Data Sheet'!G24 -> 2260 | I12: ='Data Sheet'!H24 -> 2154 | ... L12: ='Data Sheet'!K24 -> 2773 | M12: =Calculation!L13 -> 2959.1055 | N12: =Calculation!M13 -> 3116.3916 | O12: =Calculation!N13 -> 3292.54 | P12: =Calculation!O13 -> 3488.3011 | Q12: =Calculation!P13 -> 3668.3166
B13: EBITDA | C13: =C8-SUM(C11:C12) -> 6047 | D13: =D8-SUM(D11:D12) -> 7276 | E13: =E8-SUM(E11:E12) -> 8637 | F13: =F8-SUM(F11:F12) -> 9600 | G13: =G8-SUM(G11:G12) -> 11324 | H13: =H8-SUM(H11:H12) -> 12503 | I13: =I8-SUM(I11:I12) -> 13632 | J13: =J8-SUM(J11:J12) -> 14190 | ... Q13: =Q8-SUM(Q11:Q12) -> 20404.04
B14: EBITDA Margin | C14: =C13/C5 -> 0.18962057 | D14: =D13/D5 -> 0.21074584 | E14: =E13/E5 -> 0.22595751 | F14: =F13/F5 -> 0.24751837 | G14: =G13/G5 -> 0.24619532 | H14: =H13/H5 -> 0.24423261 | I14: =I13/I5 -> 0.2304883 | J14: =J13/J5 -> 0.2346657 | ... Q14: =Q13/Q5 -> 0.24069735
B16: ='Data Sheet'!A26 -> Depreciation | C16: ='Data Sheet'!B26 -> 396 | D16: ='Data Sheet'!C26 -> 478 | E16: ='Data Sheet'!D26 -> 524 | F16: ='Data Sheet'!E26 -> 938 | G16: ='Data Sheet'!F26 -> 1012 | H16: ='Data Sheet'!G26 -> 1025 | I16: ='Data Sheet'!H26 -> 1030 | ... L16: ='Data Sheet'!K26 -> 1186 | M16: =Calculation!L18 -> 1089.7051 | N16: =Calculation!M18 -> 1113.2103 | O16: =Calculation!N18 -> 1136.5066 | P16: =Calculation!O18 -> 1162.9514 | Q16: =Calculation!P18 -> 1184.64
B17: EBIT | C17: =C13-C16 -> 5651 | D17: =D13-D16 -> 6798 | E17: =E13-E16 -> 8113 | F17: =F13-F16 -> 8662 | G17: =G13-G16 -> 10312 | H17: =H13-H16 -> 11478 | I17: =I13-I16 -> 12602 | J17: =J13-J16 -> 13093 | ... Q17: =Q13-Q16 -> 19219.4
B18: EBIT Margin | C18: =C17/C5 -> 0.17720288 | D18: =D17/D5 -> 0.1969008 | E18: =E17/E5 -> 0.21224885 | F18: =F17/F5 -> 0.22333376 | G18: =G17/G5 -> 0.22419341 | H18: =H17/H5 -> 0.22421034 | I18: =I17/I5 -> 0.21307318 | J18: =J17/J5 -> 0.21652417 | ... Q18: =Q17/Q5 -> 0.22672268
B20: ='Data Sheet'!A27 -> Interest | C20: ='Data Sheet'!B27 -> 22 | D20: ='Data Sheet'!C27 -> 20 | E20: ='Data Sheet'!D27 -> 28 | F20: ='Data Sheet'!E27 -> 106 | G20: ='Data Sheet'!F27 -> 108 | H20: ='Data Sheet'!G27 -> 98 | I20: ='Data Sheet'!H27 -> 101 | ... L20: ='Data Sheet'!K27 -> 363 | M20: =Calculation!R31 -> 228.37228 | N20: =Calculation!S31 -> 241.14271 | O20: =Calculation!T31 -> 259.04514 | P20: =Calculation!U31 -> 280.75238 | Q20: =Calculation!V31 -> 279.00611
B21: ='Data Sheet'!A25 -> Other Income | C21: ='Data Sheet'!B25 -> 767 | D21: ='Data Sheet'!C25 -> 507 | E21: ='Data Sheet'!D25 -> 437 | F21: ='Data Sheet'!E25 -> 536 | G21: ='Data Sheet'!F25 -> 286 | H21: ='Data Sheet'!G25 -> 359 | I21: ='Data Sheet'!H25 -> 578 | ... L21: ='Data Sheet'!K25 -> 5572 | M21: =Calculation!L31 -> 1798.4906 | N21: =Calculation!M31 -> 2135.5552 | O21: =Calculation!N31 -> 2529.3549 | P21: =Calculation!O31 -> 2963.3209 | Q21: =Calculation!P31 -> 3411.8705
B22: EBT | C22: =(C17+C21)-C20 -> 6396 | D22: =(D17+D21)-D20 -> 7285 | E22: =(E17+E21)-E20 -> 8522 | F22: =(F17+F21)-F20 -> 9092 | G22: =(G17+G21)-G20 -> 10490 | H22: =(H17+H21)-H20 -> 11739 | I22: =(I17+I21)-I20 -> 13079 | J22: =(J17+J21)-J20 -> 13675 | ... Q22: =(Q17+Q21)-Q20 -> 22352.264
B23: EBT Margin | C23: =C22/C5 -> 0.20056444 | D23: =D22/D5 -> 0.21100652 | E23: =E22/E5 -> 0.22294893 | F23: =F22/F5 -> 0.23442052 | G23: =G22/G5 -> 0.22806331 | H23: =H22/H5 -> 0.22930869 | I23: =I22/I5 -> 0.22113824 | J23: =J22/J5 -> 0.22614894 | ... Q23: =Q22/Q5 -> 0.26367968
B25: ='Data Sheet'!A29 -> Tax | C25: ='Data Sheet'!B29 -> 1906 | D25: ='Data Sheet'!C29 -> 2048 | E25: ='Data Sheet'!D29 -> 2486 | F25: ='Data Sheet'!E29 -> 2354 | G25: ='Data Sheet'!F29 -> 2536 | H25: ='Data Sheet'!G29 -> 2921 | I25: ='Data Sheet'!H29 -> 3117 | ... L25: ='Data Sheet'!K29 -> 3060 | M25: =Calculation!L37 -> 4401.0339 | N25: =Calculation!M37 -> 4593.6818 | O25: =Calculation!N37 -> 4751.7347 | P25: =Calculation!O37 -> 4824.3691 | Q25: =Calculation!P37 -> 4999.0492
B26: Net Profit | C26: =C22-C25 -> 4490 | D26: =D22-D25 -> 5237 | E26: =E22-E25 -> 6036 | F26: =F22-F25 -> 6738 | G26: =G22-G25 -> 7954 | H26: =H22-H25 -> 8818 | I26: =I22-I25 -> 9962 | J26: =J22-J25 -> 10114 | ... Q26: =Q22-Q25 -> 17353.215
B27: Net Profit Margin | C27: =C26/C5 -> 0.14079649 | D27: =D26/D5 -> 0.15168718 | E27: =E26/E5 -> 0.15791126 | F27: =F26/F5 -> 0.17372696 | G27: =G26/G5 -> 0.17292808 | H27: =H26/H5 -> 0.17225011 | I27: =I26/I5 -> 0.16843636 | J27: =J26/J5 -> 0.16725926 | ... Q27: =Q26/Q5 -> 0.20470813
A30: # | B30: Balance Sheet(in CR)
B31: ='Data Sheet'!A57 -> Equity Share Capital | C31: ='Data Sheet'!B57 -> 216 | D31: ='Data Sheet'!C57 -> 216 | E31: ='Data Sheet'!D57 -> 216 | F31: ='Data Sheet'!E57 -> 216 | G31: ='Data Sheet'!F57 -> 235 | H31: ='Data Sheet'!G57 -> 235 | I31: ='Data Sheet'!H57 -> 235 | ... K31: ='Data Sheet'!J57 -> 235 | L31: ='Data Sheet'!$K57 -> 235 | M31: ='Data Sheet'!$K57 -> 235 | N31: ='Data Sheet'!$K57 -> 235 | O31: ='Data Sheet'!$K57 -> 235 | P31: ='Data Sheet'!$K57 -> 235 | Q31: ='Data Sheet'!$K57 -> 235
B32: ='Data Sheet'!A58 -> Reserves | C32: ='Data Sheet'!B58 -> 6274 | D32: ='Data Sheet'!C58 -> 6859 | E32: ='Data Sheet'!D58 -> 7443 | F32: ='Data Sheet'!E58 -> 7815 | G32: ='Data Sheet'!F58 -> 47199 | H32: ='Data Sheet'!G58 -> 48525 | I32: ='Data Sheet'!H58 -> 49986 | ... L32: ='Data Sheet'!K58 -> 48988 | M32: =Calculation!R44 -> 50800.956 | N32: =Calculation!S44 -> 52681.921 | O32: =Calculation!T44 -> 54503.012 | P32: =Calculation!U44 -> 56219.91 | Q32: =Calculation!V44 -> 57829.611
B34: Liabilities
B35: Current Liabilities
B36: ='Manual Data'!B39 -> Trade Payables | C36: ='Manual Data'!C39 -> 6006 | D36: ='Manual Data'!D39 -> 7013 | E36: ='Manual Data'!E39 -> 7070 | F36: ='Manual Data'!F39 -> 7399 | G36: ='Manual Data'!G39 -> 8627 | H36: ='Manual Data'!H39 -> 8864 | I36: ='Manual Data'!I39 -> 9391 | ... L36: ='Manual Data'!L39 -> 12913 | M36: =Calculation!L46 -> 12895.106 | N36: =Calculation!M46 -> 13567.994 | O36: =Calculation!N46 -> 14122.085 | P36: =Calculation!O46 -> 14794.543 | Q36: =Calculation!P46 -> 15404.403
B37: ='Manual Data'!B40 -> Advance from Customers | C37: ='Manual Data'!C40 -> 70 | D37: ='Manual Data'!D40 -> 55 | E37: ='Manual Data'!E40 -> 39 | F37: ='Manual Data'!F40 -> 154 | G37: ='Manual Data'!G40 -> 93 | H37: ='Manual Data'!H40 -> 113 | I37: ='Manual Data'!I40 -> 86 | ... L37: ='Manual Data'!L40 -> 0 | M37: =Calculation!L50 -> 111.01986 | N37: =Calculation!M50 -> 112.60285 | O37: =Calculation!N50 -> 117.93169 | P37: =Calculation!O50 -> 127.80588 | Q37: =Calculation!P50 -> 113.48286
B38: Total Current Liabilities | C38: =SUM(C36:C37) -> 6076 | D38: =SUM(D36:D37) -> 7068 | E38: =SUM(E36:E37) -> 7109 | F38: =SUM(F36:F37) -> 7553 | G38: =SUM(G36:G37) -> 8720 | H38: =SUM(H36:H37) -> 8977 | I38: =SUM(I36:I37) -> 9477 | J38: =SUM(J36:J37) -> 10237 | ... Q38: =SUM(Q36:Q37) -> 15517.886
B40: Non-Current Liabilities
B41: ='Data Sheet'!A59 -> Borrowings | C41: ='Data Sheet'!B59 -> 0 | D41: ='Data Sheet'!C59 -> 0 | E41: ='Data Sheet'!D59 -> 0 | F41: ='Data Sheet'!E59 -> 0 | G41: ='Data Sheet'!F59 -> 943 | H41: ='Data Sheet'!G59 -> 971 | I41: ='Data Sheet'!H59 -> 1039 | ... K41: ='Data Sheet'!J59 -> 1537 | L41: ='Data Sheet'!$K$59 -> 1325 | M41: =Calculation!R30 -> 1325 | N41: =Calculation!S30 -> 1325 | O41: =Calculation!T30 -> 1325 | P41: =Calculation!U30 -> 1325 | Q41: =Calculation!V30 -> 1325
B42: ='Data Sheet'!A60 -> Other Liabilities | C42: ='Data Sheet'!B60-SUM(C36:C37) -> 2185 | D42: ='Data Sheet'!C60-SUM(D36:D37) -> 3006 | E42: ='Data Sheet'!D60-SUM(E36:E37) -> 3097 | F42: ='Data Sheet'!E60-SUM(F36:F37) -> 4018 | G42: ='Data Sheet'!F60-SUM(G36:G37) -> 11019 | H42: ='Data Sheet'!G60-SUM(H36:H37) -> 11029 | I42: ='Data Sheet'!H60-SUM(I36:I37) -> 11088 | J42: ='Data Sheet'!I60-SUM(J36:J37) -> 14492 | ... L42: ='Data Sheet'!K60-SUM(L36:L37) -> 14521 | M42: =Calculation!L54 -> 12090.09 | N42: =Calculation!M54 -> 13514.816 | O42: =Calculation!N54 -> 14958.484 | P42: =Calculation!O54 -> 16602.88 | Q42: =Calculation!P54 -> 18236.572
B43: Total Non-Current Liabilities | C43: =SUM(C41:C42) -> 2185 | D43: =SUM(D41:D42) -> 3006 | E43: =SUM(E41:E42) -> 3097 | F43: =SUM(F41:F42) -> 4018 | G43: =SUM(G41:G42) -> 11962 | H43: =SUM(H41:H42) -> 12000 | I43: =SUM(I41:I42) -> 12127 | J43: =SUM(J41:J42) -> 15866 | ... Q43: =SUM(Q41:Q42) -> 19561.572
B45: Total Liabilities | C45: =SUM(C43,C38,C31:C32) -> 14751 | D45: =SUM(D43,D38,D31:D32) -> 17149 | E45: =SUM(E43,E38,E31:E32) -> 17865 | F45: =SUM(F43,F38,F31:F32) -> 19602 | G45: =SUM(G43,G38,G31:G32) -> 68116 | H45: =SUM(H43,H38,H31:H32) -> 69737 | I45: =SUM(I43,I38,I31:I32) -> 71825 | J45: =SUM(J43,J38,J31:J32) -> 77076 | ... Q45: =SUM(Q43,Q38,Q31:Q32) -> 93144.068
B47: Assets
B48: Non-Current Assets
B49: ='Data Sheet'!A62 -> Net Block | C49: ='Data Sheet'!B62 -> 4024 | D49: ='Data Sheet'!C62 -> 4142 | E49: ='Data Sheet'!D62 -> 4343 | F49: ='Data Sheet'!E62 -> 5056 | G49: ='Data Sheet'!F62 -> 51027 | H49: ='Data Sheet'!G62 -> 51034 | I49: ='Data Sheet'!H62 -> 51405 | ... L49: ='Data Sheet'!K62 -> 52419 | M49: =Calculation!R24 -> 53285.88 | N49: =Calculation!S24 -> 54205.437 | O49: =Calculation!T24 -> 55229.184 | P49: =Calculation!U24 -> 56404.477 | Q49: =Calculation!V24 -> 57744.637
B50: ='Data Sheet'!A63 -> Capital Work in Progress | C50: ='Data Sheet'!B63 -> 203 | D50: ='Data Sheet'!C63 -> 430 | E50: ='Data Sheet'!D63 -> 373 | F50: ='Data Sheet'!E63 -> 513 | G50: ='Data Sheet'!F63 -> 623 | H50: ='Data Sheet'!G63 -> 901 | I50: ='Data Sheet'!H63 -> 1020 | ... L50: ='Data Sheet'!K63 -> 833 | M50: =Calculation!L58 -> 2359.2155 | N50: =Calculation!M58 -> 2366.4696 | O50: =Calculation!N58 -> 2078.9207 | P50: =Calculation!O58 -> 1851.045 | Q50: =Calculation!P58 -> 1498.6302
B51: ='Data Sheet'!A64 -> Investments | C51: ='Data Sheet'!B64 -> 3779 | D51: ='Data Sheet'!C64 -> 3111 | E51: ='Data Sheet'!D64 -> 2949 | F51: ='Data Sheet'!E64 -> 1500 | G51: ='Data Sheet'!F64 -> 2995 | H51: ='Data Sheet'!G64 -> 4122 | I51: ='Data Sheet'!H64 -> 3794 | ... L51: ='Data Sheet'!K64 -> 8879 | M51: =Calculation!L74 -> 5890.533 | N51: =Calculation!M74 -> 5959.5745 | O51: =Calculation!N74 -> 6196.8551 | P51: =Calculation!O74 -> 6525.0657 | Q51: =Calculation!P74 -> 7184.4095
B52: ='Data Sheet'!A65 -> Other Assets | C52: ='Data Sheet'!B65-SUM(C56:C58) -> 1784 | D52: ='Data Sheet'!C65-SUM(D56:D58) -> 2587 | E52: ='Data Sheet'!D65-SUM(E56:E58) -> 2417 | F52: ='Data Sheet'!E65-SUM(F56:F58) -> 3834 | G52: ='Data Sheet'!F65-SUM(G56:G58) -> 4119 | H52: ='Data Sheet'!G65-SUM(H56:H58) -> 4240 | I52: ='Data Sheet'!H65-SUM(I56:I58) -> 4418 | J52: ='Data Sheet'!I65-SUM(J56:J58) -> 4571 | ... L52: ='Data Sheet'!K65-SUM(L56:L58) -> 5601 | M52: =Calculation!L62 -> 5496.2285 | N52: =Calculation!M62 -> 5961.8282 | O52: =Calculation!N62 -> 6316.6573 | P52: =Calculation!O62 -> 6776.0204 | Q52: =Calculation!P62 -> 6963.2005
B53: Total Non-Current Assests | C53: =SUM(C49:C52) -> 9790 | D53: =SUM(D49:D52) -> 10270 | E53: =SUM(E49:E52) -> 10082 | F53: =SUM(F49:F52) -> 10903 | G53: =SUM(G49:G52) -> 58764 | H53: =SUM(H49:H52) -> 60297 | I53: =SUM(I49:I52) -> 60637 | J53: =SUM(J49:J52) -> 63358 | ... Q53: =SUM(Q49:Q52) -> 73390.877
B55: Current Assets
B56: ='Data Sheet'!A67 -> Receivables | C56: ='Data Sheet'!B67 -> 928 | D56: ='Data Sheet'!C67 -> 1147 | E56: ='Data Sheet'!D67 -> 1673 | F56: ='Data Sheet'!E67 -> 1046 | G56: ='Data Sheet'!F67 -> 1648 | H56: ='Data Sheet'!G67 -> 1932 | I56: ='Data Sheet'!H67 -> 2735 | ... L56: ='Data Sheet'!K67 -> 3037 | M56: =Calculation!L66 -> 2816.0407 | N56: =Calculation!M66 -> 3051.3817 | O56: =Calculation!N66 -> 3272.5948 | P56: =Calculation!O66 -> 3421.4265 | Q56: =Calculation!P66 -> 3710.4424
B57: ='Data Sheet'!A68 -> Inventory | C57: ='Data Sheet'!B68 -> 2362 | D57: ='Data Sheet'!C68 -> 2359 | E57: ='Data Sheet'!D68 -> 2422 | F57: ='Data Sheet'!E68 -> 2636 | G57: ='Data Sheet'!F68 -> 3383 | H57: ='Data Sheet'!G68 -> 3890 | I57: ='Data Sheet'!H68 -> 4031 | ... L57: ='Data Sheet'!K68 -> 4383 | M57: =Calculation!L70 -> 4844.3111 | N57: =Calculation!M70 -> 5073.3945 | O57: =Calculation!N70 -> 5340.1237 | P57: =Calculation!O70 -> 5649.1493 | Q57: =Calculation!P70 -> 5926.2702
B58: ='Data Sheet'!A69 -> Cash & Bank | C58: ='Data Sheet'!B69 -> 1671 | D58: ='Data Sheet'!C69 -> 3373 | E58: ='Data Sheet'!D69 -> 3688 | F58: ='Data Sheet'!E69 -> 5017 | G58: ='Data Sheet'!F69 -> 4321 | H58: ='Data Sheet'!G69 -> 3618 | I58: ='Data Sheet'!H69 -> 4422 | ... L58: ='Data Sheet'!K69 -> 2830 | M58: =L58+M99 -> 3296.3032 | N58: =M58+N99 -> 1705.9715 | O58: =N58+O99 -> -2.2786083 | P58: =O58+P99 -> -2343.0485 | Q58: =P58+Q99 -> -5181.2173
B59: Total Current Assets | C59: =SUM(C56:C58) -> 4961 | D59: =SUM(D56:D58) -> 6879 | E59: =SUM(E56:E58) -> 7783 | F59: =SUM(F56:F58) -> 8699 | G59: =SUM(G56:G58) -> 9352 | H59: =SUM(H56:H58) -> 9440 | I59: =SUM(I56:I58) -> 11188 | J59: =SUM(J56:J58) -> 13718 | ... Q59: =SUM(Q56:Q58) -> 4455.4953
B61: Total Assets | C61: =SUM(C59,C53) -> 14751 | D61: =SUM(D59,D53) -> 17149 | E61: =SUM(E59,E53) -> 17865 | F61: =SUM(F59,F53) -> 19602 | G61: =SUM(G59,G53) -> 68116 | H61: =SUM(H59,H53) -> 69737 | I61: =SUM(I59,I53) -> 71825 | J61: =SUM(J59,J53) -> 77076 | ... Q61: =SUM(Q59,Q53) -> 77846.372
A64: # | B64: ='Manual Data'!B1&"(in CR)" -> Cash-Flows(in CR)
B65: ='Manual Data'!B2 -> Cash from Operating Activity
B66: ='Manual Data'!B3 -> Profit from operations | C66: ='Manual Data'!C3 -> 6219 | D66: ='Manual Data'!D3 -> 7237 | E66: ='Manual Data'!E3 -> 8674 | F66: ='Manual Data'!F3 -> 9473 | G66: ='Manual Data'!G3 -> 11380 | H66: ='Manual Data'!H3 -> 12473 | I66: ='Manual Data'!I3 -> 13557 | ... L66: ='Manual Data'!L3 -> 14538 | M66: =M17 -> 16015.488 | N66: =N17 -> 17105.503 | O66: =O17 -> 17912.255 | P66: =P17 -> 18472.559 | Q66: =Q17 -> 19219.4
B67: ='Manual Data'!B4 -> Receivables | C67: ='Manual Data'!C4 -> 131 | D67: ='Manual Data'!D4 -> 0 | E67: ='Manual Data'!E4 -> 0 | F67: ='Manual Data'!F4 -> 0 | G67: ='Manual Data'!G4 -> 0 | H67: ='Manual Data'!H4 -> 0 | I67: ='Manual Data'!I4 -> 0 | ... L67: ='Manual Data'!L4 -> 0 | M67: =IF(M56>L56,-ABS(M56-L56),ABS(M56-L56)) -> 220.95926 | N67: =IF(N56>M56,-ABS(N56-M56),ABS(N56-M56)) -> -235.34098 | O67: =IF(O56>N56,-ABS(O56-N56),ABS(O56-N56)) -> -221.21306 | P67: =IF(P56>O56,-ABS(P56-O56),ABS(P56-O56)) -> -148.83167 | Q67: =IF(Q56>P56,-ABS(Q56-P56),ABS(Q56-P56)) -> -289.01594
B68: ='Manual Data'!B5 -> Inventory | C68: ='Manual Data'!C5 -> 38 | D68: ='Manual Data'!D5 -> -162 | E68: ='Manual Data'!E5 -> -195 | F68: ='Manual Data'!F5 -> -369 | G68: ='Manual Data'!G5 -> -472 | H68: ='Manual Data'!H5 -> -737 | I68: ='Manual Data'!I5 -> -332 | ... L68: ='Manual Data'!L5 -> -630 | M68: =IF(M57>L57,-ABS(M57-L57),ABS(M57-L57)) -> -461.31107 | N68: =IF(N57>M57,-ABS(N57-M57),ABS(N57-M57)) -> -229.08346 | O68: =IF(O57>N57,-ABS(O57-N57),ABS(O57-N57)) -> -266.72917 | P68: =IF(P57>O57,-ABS(P57-O57),ABS(P57-O57)) -> -309.02562 | Q68: =IF(Q57>P57,-ABS(Q57-P57),ABS(Q57-P57)) -> -277.12085 | U68: s
B69: ='Manual Data'!B6 -> Payables | C69: ='Manual Data'!C6 -> 508 | D69: ='Manual Data'!D6 -> 0 | E69: ='Manual Data'!E6 -> 0 | F69: ='Manual Data'!F6 -> 0 | G69: ='Manual Data'!G6 -> 0 | H69: ='Manual Data'!H6 -> 0 | I69: ='Manual Data'!I6 -> 0 | ... L69: ='Manual Data'!L6 -> 0 | M69: =IF(M36>L36,ABS(M36-L36),-ABS(M36-L36)) -> -17.89389 | N69: =IF(N36>M36,ABS(N36-M36),-ABS(N36-M36)) -> 672.8883 | O69: =IF(O36>N36,ABS(O36-N36),-ABS(O36-N36)) -> 554.09088 | P69: =IF(P36>O36,ABS(P36-O36),-ABS(P36-O36)) -> 672.45785 | Q69: =IF(Q36>P36,ABS(Q36-P36),-ABS(Q36-P36)) -> 609.85989
B70: ='Manual Data'!B7 -> Loans Advances | C70: ='Manual Data'!C7 -> -46 | D70: ='Manual Data'!D7 -> 0 | E70: ='Manual Data'!E7 -> 0 | F70: ='Manual Data'!F7 -> 0 | G70: ='Manual Data'!G7 -> 0 | H70: ='Manual Data'!H7 -> 0 | I70: ='Manual Data'!I7 -> 0 | ... L70: ='Manual Data'!L7 -> 0 | M70: =IF(M52>L52,-ABS(M52-L52),ABS(M52-L52)) -> 104.77146 | N70: =IF(N52>M52,-ABS(N52-M52),ABS(N52-M52)) -> -465.59962 | O70: =IF(O52>N52,-ABS(O52-N52),ABS(O52-N52)) -> -354.82914 | P70: =IF(P52>O52,-ABS(P52-O52),ABS(P52-O52)) -> -459.36313 | Q70: =IF(Q52>P52,-ABS(Q52-P52),ABS(Q52-P52)) -> -187.18002
B71: ='Manual Data'!B8 -> Other WC items | C71: ='Manual Data'!C8 -> -93 | D71: ='Manual Data'!D8 -> 1026 | E71: ='Manual Data'!E8 -> -66 | F71: ='Manual Data'!F8 -> 666 | G71: ='Manual Data'!G8 -> 416 | H71: ='Manual Data'!H8 -> -52 | I71: ='Manual Data'!I8 -> -531 | ... L71: ='Manual Data'!L8 -> 1314 | M71: =IF(M37>L37,ABS(M37-L37),-ABS(M37-L37)) -> 111.01986 | N71: =IF(N37>M37,ABS(N37-M37),-ABS(N37-M37)) -> 1.5829874 | O71: =IF(O37>N37,ABS(O37-N37),-ABS(O37-N37)) -> 5.3288426 | P71: =IF(P37>O37,ABS(P37-O37),-ABS(P37-O37)) -> 9.874188 | Q71: =IF(Q37>P37,ABS(Q37-P37),-ABS(Q37-P37)) -> -14.323012
B72: ='Manual Data'!B9 -> Working capital changes | C72: ='Manual Data'!C9 -> 538 | D72: ='Manual Data'!D9 -> 864 | E72: ='Manual Data'!E9 -> -261 | F72: ='Manual Data'!F9 -> 297 | G72: ='Manual Data'!G9 -> -56 | H72: ='Manual Data'!H9 -> -789 | I72: ='Manual Data'!I9 -> -863 | ... L72: ='Manual Data'!L9 -> 684 | M72: =SUM(M67:M71) -> -42.454388 | N72: =SUM(N67:N71) -> -255.55277 | O72: =SUM(O67:O71) -> -283.35165 | P72: =SUM(P67:P71) -> -234.88839 | Q72: =SUM(Q67:Q71) -> -157.77993
B73: ='Manual Data'!B10 -> Direct taxes | C73: ='Manual Data'!C10 -> -1783 | D73: ='Manual Data'!D10 -> -2188 | E73: ='Manual Data'!E10 -> -2685 | F73: ='Manual Data'!F10 -> -2465 | G73: ='Manual Data'!G10 -> -2367 | H73: ='Manual Data'!H10 -> -2720 | I73: ='Manual Data'!I10 -> -3068 | ... L73: ='Manual Data'!L10 -> -4726 | M73: =-M25 -> -4401.0339 | N73: =-N25 -> -4593.6818 | O73: =-O25 -> -4751.7347 | P73: =-P25 -> -4824.3691 | Q73: =-Q25 -> -4999.0492
B74: ='Manual Data'!B11 -> Other operating items | C74: ='Manual Data'!C11 -> -21 | D74: ='Manual Data'!D11 -> 0 | E74: ='Manual Data'!E11 -> 0 | F74: ='Manual Data'!F11 -> 0 | G74: ='Manual Data'!G11 -> 0 | H74: ='Manual Data'!H11 -> 0 | I74: ='Manual Data'!I11 -> 0 | ... Q74: ='Manual Data'!Q11 -> 0
B75: ='Manual Data'!B12 -> Cash-Flow from Operating Activity | C75: ='Manual Data'!C12 -> 4953 | D75: ='Manual Data'!D12 -> 5913 | E75: ='Manual Data'!E12 -> 5728 | F75: ='Manual Data'!F12 -> 7305 | G75: ='Manual Data'!G12 -> 8957 | H75: ='Manual Data'!H12 -> 8964 | I75: ='Manual Data'!I12 -> 9626 | ... L75: ='Manual Data'!L12 -> 10496 | M75: =SUM(M66,M72,M73,M74) -> 11571.999 | N75: =SUM(N66,N72,N73,N74) -> 12256.268 | O75: =SUM(O66,O72,O73,O74) -> 12877.168 | P75: =SUM(P66,P72,P73,P74) -> 13413.301 | Q75: =SUM(Q66,Q72,Q73,Q74) -> 14062.571
B77: ='Manual Data'!B14 -> Cash from Investing Activity
B78: ='Manual Data'!B15 -> Fixed assets purchased | C78: ='Manual Data'!C15 -> -1024 | D78: ='Manual Data'!D15 -> -853 | E78: ='Manual Data'!E15 -> -728 | F78: ='Manual Data'!F15 -> -765 | G78: ='Manual Data'!G15 -> -4051 | H78: ='Manual Data'!H15 -> -919 | I78: ='Manual Data'!I15 -> -1041 | ... L78: ='Manual Data'!L15 -> -1274 | M78: =-((M49-L49)+(M50-L50)+M16) -> -3482.8007 | N78: =-((N49-M49)+(N50-M50)+N16) -> -2040.0211 | O78: =-((O49-N49)+(O50-N50)+O16) -> -1872.7043 | P78: =-((P49-O49)+(P50-O50)+P16) -> -2110.3688 | Q78: =-((Q49-P49)+(Q50-P50)+Q16) -> -2172.3853
B79: ='Manual Data'!B16 -> Fixed assets sold | C79: ='Manual Data'!C16 -> 172 | D79: ='Manual Data'!D16 -> 26 | E79: ='Manual Data'!E16 -> 4 | F79: ='Manual Data'!F16 -> 52 | G79: ='Manual Data'!G16 -> 97 | H79: ='Manual Data'!H16 -> 175 | I79: ='Manual Data'!I16 -> 180 | ... L79: ='Manual Data'!L16 -> 29 | M79: =AVERAGE(C79:L79) -> 76.8 | N79: =AVERAGE(D79:M79) -> 67.28 | O79: =AVERAGE(E79:N79) -> 71.408 | P79: =AVERAGE(F79:O79) -> 78.1488 | Q79: =AVERAGE(G79:P79) -> 80.76368
B80: ='Manual Data'!B17 -> Investments purchased | C80: ='Manual Data'!C17 -> -26230 | D80: ='Manual Data'!D17 -> -47755 | E80: ='Manual Data'!E17 -> -70434 | F80: ='Manual Data'!F17 -> -34074 | G80: ='Manual Data'!G17 -> -38450 | H80: ='Manual Data'!H17 -> -47928 | I80: ='Manual Data'!I17 -> -22631 | ... L80: ='Manual Data'!L17 -> -23058 | M80: 0 | N80: =IF(N51>M51,-ABS(N51-M51),ABS(N51-M51)) -> -69.041498 | O80: =IF(O51>N51,-ABS(O51-N51),ABS(O51-N51)) -> -237.28066 | P80: =IF(P51>O51,-ABS(P51-O51),ABS(P51-O51)) -> -328.21057 | Q80: =IF(Q51>P51,-ABS(Q51-P51),ABS(Q51-P51)) -> -659.34376
B81: ='Manual Data'!B18 -> Investments sold | C81: ='Manual Data'!C18 -> 25260 | D81: ='Manual Data'!D18 -> 48534 | E81: ='Manual Data'!E18 -> 70761 | F81: ='Manual Data'!F18 -> 35656 | G81: ='Manual Data'!G18 -> 37076 | H81: ='Manual Data'!H18 -> 47173 | I81: ='Manual Data'!I18 -> 23363 | ... L81: ='Manual Data'!L18 -> 22609 | M81: =IF(M51>L51,-ABS(M51-L51),ABS(M51-L51)) -> 2988.467 | N81: =-N80 -> 69.041498 | O81: =-O80 -> 237.28066 | P81: =-P80 -> 328.21057 | Q81: =-Q80 -> 659.34376
B82: ='Manual Data'!B19 -> Interest received | C82: ='Manual Data'!C19 -> 266 | D82: ='Manual Data'!D19 -> 229 | E82: ='Manual Data'!E19 -> 308 | F82: ='Manual Data'!F19 -> 359 | G82: ='Manual Data'!G19 -> 285 | H82: ='Manual Data'!H19 -> 171 | I82: ='Manual Data'!I19 -> 273 | ... L82: ='Manual Data'!L19 -> 431 | M82: =Calculation!L78 -> 625.14808 | N82: =Calculation!M78 -> 642.26774 | O82: =Calculation!N78 -> 686.13291 | P82: =Calculation!O78 -> 723.33376 | Q82: =Calculation!P78 -> 790.57103
B83: ='Manual Data'!B20 -> Dividends received | C83: ='Manual Data'!C20 -> 178 | D83: ='Manual Data'!D20 -> 190 | E83: ='Manual Data'!E20 -> 103 | F83: ='Manual Data'!F20 -> 96 | G83: ='Manual Data'!G20 -> 102 | H83: ='Manual Data'!H20 -> 131 | I83: ='Manual Data'!I20 -> 118 | ... L83: ='Manual Data'!L20 -> 230 | M83: =Calculation!L83 -> 234.86148 | N83: =Calculation!M83 -> 233.30462 | O83: =Calculation!N83 -> 229.00659 | P83: =Calculation!O83 -> 242.45912 | Q83: =Calculation!P83 -> 247.67478
B84: ='Manual Data'!B21 -> Invest in subsidiaries | C84: ='Manual Data'!C21 -> 0 | D84: ='Manual Data'!D21 -> 0 | E84: ='Manual Data'!E21 -> 0 | F84: ='Manual Data'!F21 -> 0 | G84: ='Manual Data'!G21 -> -60 | H84: ='Manual Data'!H21 -> -300 | I84: ='Manual Data'!I21 -> -264 | ... L84: ='Manual Data'!L21 -> -3530 | M84: =AVERAGE(C84:L84) -> -415.9 | N84: =AVERAGE(D84:M84) -> -457.49 | O84: =AVERAGE(E84:N84) -> -503.239 | P84: =AVERAGE(F84:O84) -> -553.5629 | Q84: =AVERAGE(G84:P84) -> -608.91919
B85: ='Manual Data'!B22 -> Loans to subsidiaries | C85: ='Manual Data'!C22 -> -84 | D85: ='Manual Data'!D22 -> -183 | E85: ='Manual Data'!E22 -> -248 | F85: ='Manual Data'!F22 -> -292 | G85: ='Manual Data'!G22 -> -180 | H85: ='Manual Data'!H22 -> -436 | I85: ='Manual Data'!I22 -> -493 | ... L85: ='Manual Data'!L22 -> -171 | M85: =AVERAGE(C85:L85) -> -288 | N85: =AVERAGE(D85:M85) -> -308.4 | O85: =AVERAGE(E85:N85) -> -320.94 | P85: =AVERAGE(F85:O85) -> -328.234 | Q85: =AVERAGE(G85:P85) -> -331.8574
B86: ='Manual Data'!B23 -> Redemp n Canc of Shares | C86: ='Manual Data'!C23 -> 20 | D86: ='Manual Data'!D23 -> 73 | E86: ='Manual Data'!E23 -> 0 | F86: ='Manual Data'!F23 -> 0 | G86: ='Manual Data'!G23 -> 0 | H86: ='Manual Data'!H23 -> 0 | I86: ='Manual Data'!I23 -> 0 | ... K86: ='Manual Data'!K23 -> 0 | L86: ='Manual Data'!$L$23 -> 298 | M86: =AVERAGE(C86:L86) -> 39.1 | N86: =AVERAGE(D86:M86) -> 41.01 | O86: =AVERAGE(E86:N86) -> 37.811 | P86: =AVERAGE(F86:O86) -> 41.5921 | Q86: =AVERAGE(G86:P86) -> 45.75131
B87: ='Manual Data'!B24 -> Acquisition of companies | C87: ='Manual Data'!C24 -> 0 | D87: ='Manual Data'!D24 -> 0 | E87: ='Manual Data'!E24 -> 0 | F87: ='Manual Data'!F24 -> 0 | G87: ='Manual Data'!G24 -> 0 | H87: ='Manual Data'!H24 -> 0 | I87: ='Manual Data'!I24 -> 0 | ... Q87: ='Manual Data'!Q24 -> 0
B88: ='Manual Data'!B25 -> Other investing items | C88: ='Manual Data'!C25 -> 690 | D88: ='Manual Data'!D25 -> -1522 | E88: ='Manual Data'!E25 -> -30 | F88: ='Manual Data'!F25 -> 894 | G88: ='Manual Data'!G25 -> 4114 | H88: ='Manual Data'!H25 -> 201 | I88: ='Manual Data'!I25 -> -567 | ... L88: ='Manual Data'!L25 -> 963 | M88: =AVERAGE(C88:L88) -> 864.2 | N88: =AVERAGE(D88:M88) -> 881.62 | O88: =AVERAGE(E88:N88) -> 1121.982 | P88: =AVERAGE(F88:O88) -> 1237.1802 | Q88: =AVERAGE(G88:P88) -> 1271.4982
B89: ='Manual Data'!B26 -> Cash-Flow from Investing Activity | C89: ='Manual Data'!C26 -> -752 | D89: ='Manual Data'!D26 -> -1261 | E89: ='Manual Data'!E26 -> -264 | F89: ='Manual Data'!F26 -> 1926 | G89: ='Manual Data'!G26 -> -1067 | H89: ='Manual Data'!H26 -> -1732 | I89: ='Manual Data'!I26 -> -1062 | ... L89: ='Manual Data'!L26 -> -3473 | M89: =SUM(M78:M88) -> 641.87585 | N89: =SUM(N78:N88) -> -940.42876 | O89: =SUM(O78:O88) -> -550.54285 | P89: =SUM(P78:P88) -> -669.45168 | Q89: =SUM(Q78:Q88) -> -676.90284
B91: ='Manual Data'!B28 -> Cash from Financing Activity
B92: ='Manual Data'!B29 -> Proceeds from shares | C92: ='Manual Data'!C29 -> 0 | D92: ='Manual Data'!D29 -> 0 | E92: ='Manual Data'!E29 -> 0 | F92: ='Manual Data'!F29 -> 0 | G92: ='Manual Data'!G29 -> 0 | H92: ='Manual Data'!H29 -> 0 | I92: ='Manual Data'!I29 -> 0 | ... Q92: ='Manual Data'!Q29 -> 0
B93: ='Manual Data'!B30 -> Interest paid fin | C93: ='Manual Data'!C30 -> 0 | D93: ='Manual Data'!D30 -> 0 | E93: ='Manual Data'!E30 -> -3 | F93: ='Manual Data'!F30 -> -80 | G93: ='Manual Data'!G30 -> -86 | H93: ='Manual Data'!H30 -> -77 | I93: ='Manual Data'!I30 -> -76 | ... L93: ='Manual Data'!L30 -> -117 | M93: =Calculation!L87 -> -108.40056 | N93: =Calculation!M87 -> -61.79137 | O93: =Calculation!N87 -> -76.296974 | P93: =Calculation!O87 -> -86.463384 | Q93: =Calculation!P87 -> -96.377118
B94: ='Manual Data'!B31 -> Dividends paid | C94: ='Manual Data'!C31 -> -3561 | D94: ='Manual Data'!D31 -> -3896 | E94: ='Manual Data'!E31 -> -4546 | F94: ='Manual Data'!F31 -> -5196 | G94: ='Manual Data'!G31 -> -8811 | H94: ='Manual Data'!H31 -> -7519 | I94: ='Manual Data'!I31 -> -8459 | ... L94: ='Manual Data'!L31 -> -10103 | M94: =Calculation!L42 -> -11371.616 | N94: =Calculation!M42 -> -12525.269 | O94: =Calculation!N42 -> -13609.739 | P94: =Calculation!O42 -> -14613.86 | Q94: =Calculation!P42 -> -15743.515
B95: ='Manual Data'!B32 -> Financial liabilities | C95: ='Manual Data'!C32 -> 0 | D95: ='Manual Data'!D32 -> 0 | E95: ='Manual Data'!E32 -> 0 | F95: ='Manual Data'!F32 -> -352 | G95: ='Manual Data'!G32 -> -383 | H95: ='Manual Data'!H32 -> -388 | I95: ='Manual Data'!I32 -> -431 | ... K95: ='Manual Data'!K32 -> -460 | L95: ='Manual Data'!$L$32 -> -464 | M95: =AVERAGE(C95:K95) -> -267.55556 | N95: =AVERAGE(D95:L95) -> -319.11111 | O95: =AVERAGE(E95:M95) -> -348.83951 | P95: =AVERAGE(F95:N95) -> -384.2963 | Q95: =AVERAGE(G95:O95) -> -383.94513
B96: ='Manual Data'!B33 -> Other financing items | C96: ='Manual Data'!C33 -> -703 | D96: ='Manual Data'!D33 -> -755 | E96: ='Manual Data'!E33 -> -913 | F96: ='Manual Data'!F33 -> -1048 | G96: ='Manual Data'!G33 -> 0 | H96: ='Manual Data'!H33 -> 0 | I96: ='Manual Data'!I33 -> 0 | ... Q96: ='Manual Data'!Q33 -> 0
B97: ='Manual Data'!B34 -> Cash-Flow from Financing Activity | C97: ='Manual Data'!C34 -> -4264 | D97: ='Manual Data'!D34 -> -4651 | E97: ='Manual Data'!E34 -> -5462 | F97: ='Manual Data'!F34 -> -6676 | G97: ='Manual Data'!G34 -> -9280 | H97: ='Manual Data'!H34 -> -7984 | I97: ='Manual Data'!I34 -> -8966 | ... L97: ='Manual Data'!L34 -> -10684 | M97: =SUM(M92:M96) -> -11747.572 | N97: =SUM(N92:N96) -> -12906.171 | O97: =SUM(O92:O96) -> -14034.875 | P97: =SUM(P92:P96) -> -15084.62 | Q97: =SUM(Q92:Q96) -> -16223.837
B99: ='Manual Data'!B36 -> Net Cash Flow | C99: ='Manual Data'!C36 -> -63 | D99: ='Manual Data'!D36 -> 1 | E99: ='Manual Data'!E36 -> 2 | F99: ='Manual Data'!F36 -> 2555 | G99: ='Manual Data'!G36 -> -1390 | H99: ='Manual Data'!H36 -> -752 | I99: ='Manual Data'!I36 -> -402 | ... L99: ='Manual Data'!L36 -> -3661 | M99: =SUM(M97,M89,M75) -> 466.30318 | N99: =SUM(N97,N89,N75) -> -1590.3317 | O99: =SUM(O97,O89,O75) -> -1708.2501 | P99: =SUM(P97,P89,P75) -> -2340.7699 | Q99: =SUM(Q97,Q89,Q75) -> -2838.1687

Sheet Calculation
A3: ='Historical Financial Statement'!B2 -> Report Date | B3: ='Historical Financial Statement'!C2 -> 42825 | C3: ='Historical Financial Statement'!D2 -> 43190 | D3: ='Historical Financial Statement'!E2 -> 43555 | E3: ='Historical Financial Statement'!F2 -> 43921 | F3: ='Historical Financial Statement'!G2 -> 44286 | G3: ='Historical Financial Statement'!H2 -> 44651 | H3: ='Historical Financial Statement'!I2 -> 45016 | ... P3: ='Historical Financial Statement'!Q2 -> 47937
A4: ='Historical Financial Statement'!B5 -> Sales | B4: ='Historical Financial Statement'!C5 -> 31890 | C4: ='Historical Financial Statement'!D5 -> 34525 | D4: ='Historical Financial Statement'!E5 -> 38224 | E4: ='Historical Financial Statement'!F5 -> 38785 | F4: ='Historical Financial Statement'!G5 -> 45996 | G4: ='Historical Financial Statement'!H5 -> 51193 | H4: ='Historical Financial Statement'!I5 -> 59144 | ... P4: ='Historical Financial Statement'!Q5 -> 84770.523
A5: ='Historical Financial Statement'!B7 -> COGS | B5: ='Historical Financial Statement'!C7 -> 17969 | C5: ='Historical Financial Statement'!D7 -> 18750 | D5: ='Historical Financial Statement'!E7 -> 20476 | E5: ='Historical Financial Statement'!F7 -> 20071 | F5: ='Historical Financial Statement'!G7 -> 24773 | G5: ='Historical Financial Statement'!H7 -> 28384 | H5: ='Historical Financial Statement'!I7 -> 34684 | ... K5: ='Historical Financial Statement'!L7 -> 34774 | L5: =L4*$B$7 -> 38311.555 | M5: =M4*C7 -> 40282.675 | N5: =N4*D7 -> 42396.074 | O5: =O4*E7 -> 44577.915 | P5: =P4*F7 -> 46935.384
A6: COGS(%) | B6: =B5/B4 -> 0.56346817 | C6: =C5/C4 -> 0.54308472 | D6: =D5/D4 -> 0.53568439 | E6: =E5/E4 -> 0.51749388 | F6: =F5/F4 -> 0.53859031 | G6: =G5/G4 -> 0.5544508 | H6: =H5/H4 -> 0.58643311 | I6: =I5/I4 -> 0.54654451 | ... P6: =P5/P4 -> 0.55367576
A7: AvgCOGS(%) | B7: =AVERAGE(B6:K6) -> 0.5498677 | C7: =AVERAGE(C6:L6) -> 0.54850765 | D7: =AVERAGE(D6:M6) -> 0.54904995 | E7: =AVERAGE(E6:N6) -> 0.5503865 | F7: =AVERAGE(F6:O6) -> 0.55367576
A9: ='Historical Financial Statement'!B11 -> Selling and admin | B9: ='Historical Financial Statement'!C11 -> 6508 | C9: ='Historical Financial Statement'!D11 -> 7105 | D9: ='Historical Financial Statement'!E11 -> 7645 | E9: ='Historical Financial Statement'!F11 -> 7523 | F9: ='Historical Financial Statement'!G11 -> 7783 | G9: ='Historical Financial Statement'!H11 -> 8046 | H9: ='Historical Financial Statement'!I11 -> 8674 | ... K9: ='Historical Financial Statement'!L11 -> 9964 | L9: =L4*$B$11 -> 11298.279 | M9: =M4*C11 -> 11822.718 | N9: =N4*D11 -> 12479.779 | O9: =O4*E11 -> 13292.112 | P9: =P4*F11 -> 13762.782
A10: (%) | B10: =B9/B4 -> 0.20407651 | C10: =C9/C4 -> 0.2057929 | D10: =D9/D4 -> 0.20000523 | E10: =E9/E4 -> 0.19396674 | F10: =F9/F4 -> 0.16921037 | G10: =G9/G4 -> 0.15716993 | H10: =H9/H4 -> 0.146659 | I10: =I9/I4 -> 0.17466801 | ... P10: =P9/P4 -> 0.1623534
A11: Avg | B11: =AVERAGE(F10:K10) -> 0.16215888 | C11: =AVERAGE(G10:L10) -> 0.16098363 | D11: =AVERAGE(H10:M10) -> 0.16161925 | E11: =AVERAGE(I10:N10) -> 0.16411263 | F11: =AVERAGE(J10:O10) -> 0.1623534
A13: ='Historical Financial Statement'!B12 -> Other Expenses | B13: ='Historical Financial Statement'!C12 -> 1366 | C13: ='Historical Financial Statement'!D12 -> 1394 | D13: ='Historical Financial Statement'!E12 -> 1466 | E13: ='Historical Financial Statement'!F12 -> 1591 | F13: ='Historical Financial Statement'!G12 -> 2116 | G13: ='Historical Financial Statement'!H12 -> 2260 | H13: ='Historical Financial Statement'!I12 -> 2154 | ... K13: ='Historical Financial Statement'!L12 -> 2773 | L13: =L4*B15 -> 2959.1055 | M13: =C15*M4 -> 3116.3916 | N13: =D15*N4 -> 3292.54 | O13: =E15*O4 -> 3488.3011 | P13: =P4*F15 -> 3668.3166
B14: =B13/B4 -> 0.042834744 | C14: =C13/C4 -> 0.040376539 | D14: =D13/D4 -> 0.038352867 | E14: =E13/E4 -> 0.041021013 | F14: =F13/F4 -> 0.046004 | G14: =G13/G4 -> 0.044146661 | H14: =H13/H4 -> 0.036419586 | I14: =I13/I4 -> 0.044121781 | ... P14: =P13/P4 -> 0.043273493
B15: =AVERAGE(B14:K14) -> 0.042470648 | C15: =AVERAGE(C14:L14) -> 0.042434238 | D15: =AVERAGE(D14:M14) -> 0.042640008 | E15: =AVERAGE(E14:N14) -> 0.043068722 | F15: =AVERAGE(F14:O14) -> 0.043273493
A17: ='Historical Financial Statement'!B49 -> Net Block | B17: ='Historical Financial Statement'!C49 -> 4024 | C17: ='Historical Financial Statement'!D49 -> 4142 | D17: ='Historical Financial Statement'!E49 -> 4343 | E17: ='Historical Financial Statement'!F49 -> 5056 | F17: ='Historical Financial Statement'!G49 -> 51027 | G17: ='Historical Financial Statement'!H49 -> 51034 | H17: ='Historical Financial Statement'!I49 -> 51405 | ... K17: ='Historical Financial Statement'!L49 -> 52419 | L17: =R24 -> 53285.88 | M17: =S24 -> 54205.437 | N17: =T24 -> 55229.184 | O17: =U24 -> 56404.477 | P17: =V24 -> 57744.637
A18: ='Historical Financial Statement'!B16 -> Depreciation | B18: ='Historical Financial Statement'!C16 -> 396 | C18: ='Historical Financial Statement'!D16 -> 478 | D18: ='Historical Financial Statement'!E16 -> 524 | E18: ='Historical Financial Statement'!F16 -> 938 | F18: ='Historical Financial Statement'!G16 -> 1012 | G18: ='Historical Financial Statement'!H16 -> 1025 | H18: ='Historical Financial Statement'!I16 -> 1030 | ... K18: ='Historical Financial Statement'!L16 -> 1186 | L18: =K17*B20 -> 1089.7051 | M18: =L17*C20 -> 1113.2103 | N18: =D20*M17 -> 1136.5066 | O18: =E20*N17 -> 1162.9514 | P18: =F20*O17 -> 1184.64
B19: =B18/B17 -> 0.098409543 | C19: =C18/C17 -> 0.11540319 | D19: =D18/D17 -> 0.12065393 | E19: =E18/E17 -> 0.18552215 | F19: =F18/F17 -> 0.019832638 | G19: =G18/G17 -> 0.020084649 | H19: =H18/H17 -> 0.020036961 | I19: =I18/I17 -> 0.020943508 | ... P19: =P18/P17 -> 0.020515152 | R19: Fixed Assets Schedule
B20: =AVERAGE(F19:K19) -> 0.020788361 | C20: =AVERAGE(G19:L19) -> 0.020891282 | D20: =AVERAGE(H19:M19) -> 0.020966653 | E20: =AVERAGE(I19:N19) -> 0.021056828 | F20: =AVERAGE(J19:O19) -> 0.021002588 | R20: =L3 -> 46477 | S20: =M3 -> 46842 | T20: =N3 -> 47207 | U20: =O3 -> 47572 | V20: =P3 -> 47937
R21: =L4*B24 -> 1956.5852 | S21: =M4*C24 -> 2032.7671 | T21: =N4*D24 -> 2160.2533 | U21: =O4*E24 -> 2338.2444 | V21: =P4*F24 -> 2524.8001
A22: fixied assets purchased | B22: =-'Manual Data'!C15 -> 1024 | C22: =-'Manual Data'!D15 -> 853 | D22: =-'Manual Data'!E15 -> 728 | E22: =-'Manual Data'!F15 -> 765 | F22: =-'Manual Data'!G15 -> 4051 | G22: =-'Manual Data'!H15 -> 919 | H22: =-'Manual Data'!I15 -> 1041 | I22: =-'Manual Data'!J15 -> 1318 | ... K22: =-'Manual Data'!L15 -> 1274 | L22: =R21 -> 1956.5852 | M22: =S21 -> 2032.7671 | N22: =T21 -> 2160.2533 | O22: =U21 -> 2338.2444 | P22: =V21 -> 2524.8001 | R22: =K17 -> 52419 | S22: =L17 -> 53285.88 | T22: =M17 -> 54205.437 | U22: =N17 -> 55229.184 | V22: =O17 -> 56404.477 | W22: Opening
B23: =B22/B4 -> 0.032110379 | C23: =C22/C4 -> 0.024706734 | D23: =D22/D4 -> 0.019045626 | E23: =E22/E4 -> 0.01972412 | F23: =F22/F4 -> 0.088072876 | G23: =G22/G4 -> 0.017951673 | H23: =H22/H4 -> 0.017601109 | I23: =I22/I4 -> 0.021796292 | ... P23: =P22/P4 -> 0.02978394 | R23: =-L18 -> -1089.7051 | S23: =-M18 -> -1113.2103 | T23: =-N18 -> -1136.5066 | U23: =-O18 -> -1162.9514 | V23: =-P18 -> -1184.64
B24: =AVERAGE(B23:K23) -> 0.028081946 | C24: =AVERAGE(C23:L23) -> 0.027679102 | D24: =AVERAGE(D23:M23) -> 0.027976339 | E24: =AVERAGE(E23:N23) -> 0.028869411 | F24: =AVERAGE(F23:O23) -> 0.02978394 | R24: =SUM(R21:R23) -> 53285.88 | S24: =SUM(S21:S23) -> 54205.437 | T24: =SUM(T21:T23) -> 55229.184 | U24: =SUM(U21:U23) -> 56404.477 | V24: =SUM(V21:V23) -> 57744.637 | W24: Closing
R25: Debt Schedule
R26: =R20 -> 46477 | S26: =S20 -> 46842 | T26: =T20 -> 47207 | U26: =U20 -> 47572 | V26: =V20 -> 47937
A27: intrest | F27: ='Historical Financial Statement'!G20 -> 108 | G27: ='Historical Financial Statement'!H20 -> 98 | H27: ='Historical Financial Statement'!I20 -> 101 | I27: ='Historical Financial Statement'!J20 -> 302 | J27: ='Historical Financial Statement'!K20 -> 350 | K27: ='Historical Financial Statement'!L20 -> 363 | L27: =R31 -> 228.37228 | M27: =S31 -> 241.14271 | N27: =T31 -> 259.04514 | O27: =U31 -> 280.75238 | P27: =V31 -> 279.00611 | R27: ='Historical Financial Statement'!L41 -> 1325 | S27: =R30 -> 1325 | T27: =S30 -> 1325 | U27: =T30 -> 1325 | V27: =U30 -> 1325
A28: % | F28: =F27/'Historical Financial Statement'!G41 -> 0.1145281 | G28: =G27/'Historical Financial Statement'!H41 -> 0.10092688 | H28: =H27/'Historical Financial Statement'!I41 -> 0.097208855 | I28: =I27/'Historical Financial Statement'!J41 -> 0.21979622 | J28: =J27/'Historical Financial Statement'!K41 -> 0.22771633 | K28: =K27/'Historical Financial Statement'!L41 -> 0.27396226 | L28: =L27/R30 -> 0.17235644 | M28: =M27/S30 -> 0.1819945 | N28: =N27/T30 -> 0.19550577 | O28: =O27/U30 -> 0.21188859 | P28: =P27/V30 -> 0.21057065 | R28: ='Historical Financial Statement'!$L$95 -> -464 | S28: ='Historical Financial Statement'!$L$95 -> -464 | T28: ='Historical Financial Statement'!$L$95 -> -464 | U28: ='Historical Financial Statement'!$L$95 -> -464 | V28: ='Historical Financial Statement'!$L$95 -> -464
F29: =AVERAGE(F28:K28) -> 0.17235644 | G29: =AVERAGE(G28:L28) -> 0.1819945 | H29: =AVERAGE(H28:M28) -> 0.19550577 | I29: =AVERAGE(I28:N28) -> 0.21188859 | J29: =AVERAGE(J28:O28) -> 0.21057065 | R29: =-R28 -> 464 | S29: =-S28 -> 464 | T29: =-T28 -> 464 | U29: =-U28 -> 464 | V29: =-V28 -> 464
R30: =SUM(R27:R29) -> 1325 | S30: =SUM(S27:S29) -> 1325 | T30: =SUM(T27:T29) -> 1325 | U30: =SUM(U27:U29) -> 1325 | V30: =SUM(V27:V29) -> 1325
A31: ='Historical Financial Statement'!B21 -> Other Income | B31: ='Historical Financial Statement'!C21 -> 767 | C31: ='Historical Financial Statement'!D21 -> 507 | D31: ='Historical Financial Statement'!E21 -> 437 | E31: ='Historical Financial Statement'!F21 -> 536 | F31: ='Historical Financial Statement'!G21 -> 286 | G31: ='Historical Financial Statement'!H21 -> 359 | H31: ='Historical Financial Statement'!I21 -> 578 | ... K31: ='Historical Financial Statement'!L21 -> 5572 | L31: =L4*B33 -> 1798.4906 | M31: =M4*C33 -> 2135.5552 | N31: =N4*D33 -> 2529.3549 | O31: =O4*E33 -> 2963.3209 | P31: =P4*F33 -> 3411.8705 | R31: =AVERAGE(R27,R30)*F29 -> 228.37228 | S31: =AVERAGE(S27,S30)*G29 -> 241.14271 | T31: =AVERAGE(T27,T30)*H29 -> 259.04514 | U31: =AVERAGE(U27,U30)*I29 -> 280.75238 | V31: =AVERAGE(V27,V30)*J29 -> 279.00611
B32: =B31/B4 -> 0.024051427 | C32: =C31/C4 -> 0.014685011 | D32: =D31/D4 -> 0.011432608 | E32: =E31/E4 -> 0.013819776 | F32: =F31/F4 -> 0.006217932 | G32: =G31/G4 -> 0.0070126775 | H32: =H31/H4 -> 0.009772758 | I32: =I31/I4 -> 0.014619061 | ... P32: =P31/P4 -> 0.040248313
B33: =AVERAGE(F32:K32) -> 0.025812888 | C33: =AVERAGE(G32:L32) -> 0.029078714 | D33: =AVERAGE(H32:M32) -> 0.032756386 | E33: =AVERAGE(I32:N32) -> 0.036586991 | F33: =AVERAGE(J32:O32) -> 0.040248313
A36: ='Historical Financial Statement'!B17 -> EBIT | B36: ='Historical Financial Statement'!C17 -> 5651 | C36: ='Historical Financial Statement'!D17 -> 6798 | D36: ='Historical Financial Statement'!E17 -> 8113 | E36: ='Historical Financial Statement'!F17 -> 8662 | F36: ='Historical Financial Statement'!G17 -> 10312 | G36: ='Historical Financial Statement'!H17 -> 11478 | H36: ='Historical Financial Statement'!I17 -> 12602 | ... P36: ='Historical Financial Statement'!Q17 -> 19219.4
A37: ='Historical Financial Statement'!B25 -> Tax | B37: ='Historical Financial Statement'!C25 -> 1906 | C37: ='Historical Financial Statement'!D25 -> 2048 | D37: ='Historical Financial Statement'!E25 -> 2486 | E37: ='Historical Financial Statement'!F25 -> 2354 | F37: ='Historical Financial Statement'!G25 -> 2536 | G37: ='Historical Financial Statement'!H25 -> 2921 | H37: ='Historical Financial Statement'!I25 -> 3117 | ... K37: ='Historical Financial Statement'!L25 -> 3060 | L37: =B39*L36 -> 4401.0339 | M37: =C39*M36 -> 4593.6818 | N37: =N36*D39 -> 4751.7347 | O37: =E39*O36 -> 4824.3691 | P37: =F39*P36 -> 4999.0492
B38: =B37/B36 -> 0.33728544 | C38: =C37/C36 -> 0.30126508 | D38: =D37/D36 -> 0.30642179 | E38: =E37/E36 -> 0.27176172 | F38: =F37/F36 -> 0.24592708 | G38: =G37/G36 -> 0.25448684 | H38: =H37/H36 -> 0.24734169 | I38: =I37/I36 -> 0.27197739 | ... P38: =P37/P36 -> 0.26010433
B39: =AVERAGE(B38:K38) -> 0.27479862 | C39: =AVERAGE(C38:L38) -> 0.26854994 | D39: =AVERAGE(D38:M38) -> 0.26527843 | E39: =AVERAGE(E38:N38) -> 0.26116409 | F39: =AVERAGE(F38:O38) -> 0.26010433 | R39: Reserve Schedule
R40: =R26 -> 46477 | S40: =S26 -> 46842 | T40: =T26 -> 47207 | U40: =U26 -> 47572 | V40: =V26 -> 47937
A41: ='Historical Financial Statement'!B31 -> Equity Share Capital | B41: ='Historical Financial Statement'!C31 -> 216 | C41: ='Historical Financial Statement'!D31 -> 216 | D41: ='Historical Financial Statement'!E31 -> 216 | E41: ='Historical Financial Statement'!F31 -> 216 | F41: ='Historical Financial Statement'!G31 -> 235 | G41: ='Historical Financial Statement'!H31 -> 235 | H41: ='Historical Financial Statement'!I31 -> 235 | ... K41: ='Historical Financial Statement'!L31 -> 235 | R41: ='Historical Financial Statement'!L32 -> 48988 | S41: =R44 -> 50800.956 | T41: =S44 -> 52681.921 | U41: =T44 -> 54503.012 | V41: =U44 -> 56219.91
A42: ='Historical Financial Statement'!B94 -> Dividends paid | B42: ='Historical Financial Statement'!C94 -> -3561 | C42: ='Historical Financial Statement'!D94 -> -3896 | D42: ='Historical Financial Statement'!E94 -> -4546 | E42: ='Historical Financial Statement'!F94 -> -5196 | F42: ='Historical Financial Statement'!G94 -> -8811 | G42: ='Historical Financial Statement'!H94 -> -7519 | H42: ='Historical Financial Statement'!I94 -> -8459 | ... K42: ='Historical Financial Statement'!L94 -> -10103 | L42: =R43 -> -11371.616 | M42: =S43 -> -12525.269 | N42: =T43 -> -13609.739 | O42: =U43 -> -14613.86 | P42: =V43 -> -15743.515 | R42: ='Historical Financial Statement'!M26 -> 13184.572 | S42: ='Historical Financial Statement'!N26 -> 14406.233 | T42: ='Historical Financial Statement'!O26 -> 15430.83 | U42: ='Historical Financial Statement'!P26 -> 16330.758 | V42: ='Historical Financial Statement'!Q26 -> 17353.215
A43: Dividend paid (%) | B43: =ABS(B42/'Historical Financial Statement'!C26) -> 0.79309577 | C43: =ABS(C42/'Historical Financial Statement'!D26) -> 0.74393737 | D43: =ABS(D42/'Historical Financial Statement'!E26) -> 0.75314778 | E43: =ABS(E42/'Historical Financial Statement'!F26) -> 0.77114871 | F43: =ABS(F42/'Historical Financial Statement'!G26) -> 1.1077445 | G43: =ABS(G42/'Historical Financial Statement'!H26) -> 0.85268768 | H43: =ABS(H42/'Historical Financial Statement'!I26) -> 0.84912668 | I43: =ABS(I42/'Historical Financial Statement'!J26) -> 0.92920704 | ... P43: =ABS(P42/'Historical Financial Statement'!Q26) -> 0.90723905 | R43: =-'Historical Financial Statement'!M26*Calculation!B44 -> -11371.616 | S43: =-'Historical Financial Statement'!N26*Calculation!C44 -> -12525.269 | T43: =-'Historical Financial Statement'!O26*Calculation!D44 -> -13609.739 | U43: =-'Historical Financial Statement'!P26*Calculation!E44 -> -14613.86 | V43: =-'Historical Financial Statement'!Q26*Calculation!F44 -> -15743.515
A44: Average | B44: =AVERAGE(B43:K43) -> 0.86249412 | C44: =AVERAGE(C43:L43) -> 0.86943396 | D44: =AVERAGE(D43:M43) -> 0.88198362 | E44: =AVERAGE(E43:N43) -> 0.8948672 | F44: =AVERAGE(F43:O43) -> 0.90723905 | R44: =SUM(R41:R43) -> 50800.956 | S44: =SUM(S41:S43) -> 52681.921 | T44: =SUM(T41:T43) -> 54503.012 | U44: =SUM(U41:U43) -> 56219.91 | V44: =SUM(V41:V43) -> 57829.611
A46: ='Historical Financial Statement'!B36 -> Trade Payables | B46: ='Historical Financial Statement'!C36 -> 6006 | C46: ='Historical Financial Statement'!D36 -> 7013 | D46: ='Historical Financial Statement'!E36 -> 7070 | E46: ='Historical Financial Statement'!F36 -> 7399 | F46: ='Historical Financial Statement'!G36 -> 8627 | G46: ='Historical Financial Statement'!H36 -> 8864 | H46: ='Historical Financial Statement'!I36 -> 9391 | ... K46: ='Historical Financial Statement'!L36 -> 12913 | L46: =(L5*B48)/365 -> 12895.106 | M46: =(M5*C48)/365 -> 13567.994 | N46: =(N5*D48)/365 -> 14122.085 | O46: =(O5*E48)/365 -> 14794.543 | P46: =(P5*F48)/365 -> 15404.403
A47: ='Ratio Analysis'!B36 -> Payable Days | B47: ='Ratio Analysis'!C36 -> 121.99844 | C47: ='Ratio Analysis'!D36 -> 136.51973 | D47: ='Ratio Analysis'!E36 -> 126.02803 | E47: ='Ratio Analysis'!F36 -> 134.55408 | F47: ='Ratio Analysis'!G36 -> 127.10834 | G47: ='Ratio Analysis'!H36 -> 113.98534 | H47: ='Ratio Analysis'!I36 -> 98.826981 | ... K47: ='Ratio Analysis'!L36 -> 135.53934 | L47: =365/(L5/L46) -> 122.85363 | M47: =365/(M5/M46) -> 122.93915 | N47: =365/(N5/N46) -> 121.5811 | O47: =365/(O5/O46) -> 121.1364 | P47: =365/(P5/P46) -> 119.79463
A48: Average | B48: =AVERAGE(B47:K47) -> 122.85363 | C48: =AVERAGE(C47:L47) -> 122.93915 | D48: =AVERAGE(D47:M47) -> 121.5811 | E48: =AVERAGE(E47:N47) -> 121.1364 | F48: =AVERAGE(F47:O47) -> 119.79463
A50: ='Historical Financial Statement'!B37 -> Advance from Customers | B50: ='Historical Financial Statement'!C37 -> 70 | C50: ='Historical Financial Statement'!D37 -> 55 | D50: ='Historical Financial Statement'!E37 -> 39 | E50: ='Historical Financial Statement'!F37 -> 154 | F50: ='Historical Financial Statement'!G37 -> 93 | G50: ='Historical Financial Statement'!H37 -> 113 | H50: ='Historical Financial Statement'!I37 -> 86 | ... K50: ='Historical Financial Statement'!L37 -> 0 | L50: =L4*B52 -> 111.01986 | M50: =M4*C52 -> 112.60285 | N50: =N4*D52 -> 117.93169 | O50: =O4*E52 -> 127.80588 | P50: =P4*F52 -> 113.48286
A51: (%) | B51: =B50/B4 -> 0.0021950455 | C51: =C50/C4 -> 0.0015930485 | D51: =D50/D4 -> 0.0010203014 | E51: =E50/E4 -> 0.0039706072 | F51: =F50/F4 -> 0.0020219149 | G51: =G50/G4 -> 0.002207333 | H51: =H50/H4 -> 0.0014540782 | I51: =I50/I4 -> 0.0014718285 | ... P51: =P50/P4 -> 0.0013387067
A52: average | B52: =AVERAGE(B51:K51) -> 0.0015934157 | C52: =AVERAGE(C51:L51) -> 0.0015332528 | D52: =AVERAGE(D51:M51) -> 0.0015272732 | E52: =AVERAGE(E51:N51) -> 0.0015779704 | F52: =AVERAGE(F51:O51) -> 0.0013387067
A54: ='Historical Financial Statement'!B42 -> Other Liabilities | B54: ='Historical Financial Statement'!C42 -> 2185 | C54: ='Historical Financial Statement'!D42 -> 3006 | D54: ='Historical Financial Statement'!E42 -> 3097 | E54: ='Historical Financial Statement'!F42 -> 4018 | F54: ='Historical Financial Statement'!G42 -> 11019 | G54: ='Historical Financial Statement'!H42 -> 11029 | H54: ='Historical Financial Statement'!I42 -> 11088 | ... K54: ='Historical Financial Statement'!L42 -> 14521 | L54: =L4*B56 -> 12090.09 | M54: =M4*C56 -> 13514.816 | N54: =N4*D56 -> 14958.484 | O54: =O4*E56 -> 16602.88 | P54: =P4*F56 -> 18236.572
A55: (%) | B55: =B54/B4 -> 0.068516776 | C55: =C54/C4 -> 0.087067343 | D55: =D54/D4 -> 0.081022394 | E55: =E54/E4 -> 0.10359675 | F55: =F54/F4 -> 0.23956431 | G55: =G54/G4 -> 0.21543961 | H55: =H54/H4 -> 0.18747464 | I55: =I54/I4 -> 0.23965999 | ... P55: =P54/P4 -> 0.21512869
A56: Average | B56: =AVERAGE(B55:K55) -> 0.17352337 | C56: =AVERAGE(C55:L55) -> 0.18402403 | D56: =AVERAGE(D55:M55) -> 0.1937197 | E56: =AVERAGE(E55:N55) -> 0.20498943 | F56: =AVERAGE(F55:O55) -> 0.21512869
A58: ='Historical Financial Statement'!B50 -> Capital Work in Progress | B58: ='Historical Financial Statement'!C50 -> 203 | C58: ='Historical Financial Statement'!D50 -> 430 | D58: ='Historical Financial Statement'!E50 -> 373 | E58: ='Historical Financial Statement'!F50 -> 513 | F58: ='Historical Financial Statement'!G50 -> 623 | G58: ='Historical Financial Statement'!H50 -> 901 | H58: ='Historical Financial Statement'!I50 -> 1020 | ... K58: ='Historical Financial Statement'!L50 -> 833 | L58: =L17*B60 -> 2359.2155 | M58: =M17*C60 -> 2366.4696 | N58: =N17*D60 -> 2078.9207 | O58: =O17*E60 -> 1851.045 | P58: =P17*F60 -> 1498.6302
A59: (%) | B59: =B58/B17 -> 0.050447316 | C59: =C58/C17 -> 0.10381458 | D59: =D58/D17 -> 0.085885333 | E59: =E58/E17 -> 0.10146361 | F59: =F58/F17 -> 0.012209223 | G59: =G58/G17 -> 0.017654897 | H59: =H58/H17 -> 0.019842428 | I59: =I58/I17 -> 0.017468833 | ... P59: =P58/P17 -> 0.025952716
A60: Average | B60: =AVERAGE(B59:K59) -> 0.044274685 | C60: =AVERAGE(C59:L59) -> 0.043657421 | D60: =AVERAGE(D59:M59) -> 0.037641705 | E60: =AVERAGE(E59:N59) -> 0.032817343 | F60: =AVERAGE(F59:O59) -> 0.025952716
A62: ='Historical Financial Statement'!B52 -> Other Assets | B62: ='Historical Financial Statement'!C52 -> 1784 | C62: ='Historical Financial Statement'!D52 -> 2587 | D62: ='Historical Financial Statement'!E52 -> 2417 | E62: ='Historical Financial Statement'!F52 -> 3834 | F62: ='Historical Financial Statement'!G52 -> 4119 | G62: ='Historical Financial Statement'!H52 -> 4240 | H62: ='Historical Financial Statement'!I52 -> 4418 | ... K62: ='Historical Financial Statement'!L52 -> 5601 | L62: =L4*B64 -> 5496.2285 | M62: =M4*C64 -> 5961.8282 | N62: =N4*D64 -> 6316.6573 | O62: =O4*E64 -> 6776.0204 | P62: =P4*F64 -> 6963.2005
A63: (%) | B63: =B62/B4 -> 0.055942302 | C63: =C62/C4 -> 0.074931209 | D63: =D62/D4 -> 0.063232524 | E63: =E62/E4 -> 0.098852649 | F63: =F62/F4 -> 0.089551265 | G63: =G62/G4 -> 0.082823824 | H63: =H62/H4 -> 0.07469904 | I63: =I62/I4 -> 0.075592452 | ... P63: =P62/P4 -> 0.082141766
A64: Average | B64: =AVERAGE(B63:K63) -> 0.078884779 | C64: =AVERAGE(C63:L63) -> 0.081179027 | D64: =AVERAGE(D63:M63) -> 0.081803809 | E64: =AVERAGE(E63:N63) -> 0.083660937 | F64: =AVERAGE(F63:O63) -> 0.082141766
A66: ='Historical Financial Statement'!B56 -> Receivables | B66: ='Historical Financial Statement'!C56 -> 928 | C66: ='Historical Financial Statement'!D56 -> 1147 | D66: ='Historical Financial Statement'!E56 -> 1673 | E66: ='Historical Financial Statement'!F56 -> 1046 | F66: ='Historical Financial Statement'!G56 -> 1648 | G66: ='Historical Financial Statement'!H56 -> 1932 | H66: ='Historical Financial Statement'!I56 -> 2735 | ... K66: ='Historical Financial Statement'!L56 -> 3037 | L66: =L4*B68/365 -> 2816.0407 | M66: =M4*C68/365 -> 3051.3817 | N66: =N4*D68/365 -> 3272.5948 | O66: =O4*E68/365 -> 3421.4265 | P66: =P4*F68/365 -> 3710.4424
A67: ='Ratio Analysis'!B35 -> Receivable Days | B67: ='Ratio Analysis'!C35 -> 10.621511 | C67: ='Ratio Analysis'!D35 -> 12.12614 | D67: ='Ratio Analysis'!E35 -> 15.975434 | E67: ='Ratio Analysis'!F35 -> 9.843754 | F67: ='Ratio Analysis'!G35 -> 13.077659 | G67: ='Ratio Analysis'!H35 -> 13.77493 | H67: ='Ratio Analysis'!I35 -> 16.87872 | ... K67: ='Ratio Analysis'!L35 -> 17.886325 | L67: =365/(L4/L66) -> 14.752317 | M67: =365/(M4/M66) -> 15.165397 | N67: =365/(N4/N66) -> 15.469323 | O67: =365/(O4/O66) -> 15.418712 | P67: =365/(P4/P66) -> 15.976208
A68: Average | B68: =AVERAGE(B67:K67) -> 14.752317 | C68: =AVERAGE(C67:L67) -> 15.165397 | D68: =AVERAGE(D67:M67) -> 15.469323 | E68: =AVERAGE(E67:N67) -> 15.418712 | F68: =AVERAGE(F67:O67) -> 15.976208
A70: ='Historical Financial Statement'!B57 -> Inventory | B70: ='Historical Financial Statement'!C57 -> 2362 | C70: ='Historical Financial Statement'!D57 -> 2359 | D70: ='Historical Financial Statement'!E57 -> 2422 | E70: ='Historical Financial Statement'!F57 -> 2636 | F70: ='Historical Financial Statement'!G57 -> 3383 | G70: ='Historical Financial Statement'!H57 -> 3890 | H70: ='Historical Financial Statement'!I57 -> 4031 | ... K70: ='Historical Financial Statement'!L57 -> 4383 | L70: =L5*B72/365 -> 4844.3111 | M70: =M5*C72/365 -> 5073.3945 | N70: =N5*D72/365 -> 5340.1237 | O70: =O5*E72/365 -> 5649.1493 | P70: =P5*F72/365 -> 5926.2702
A71: ='Ratio Analysis'!B34 -> Inventory Days | B71: ='Ratio Analysis'!C34 -> 47.978741 | C71: ='Ratio Analysis'!D34 -> 45.921867 | D71: ='Ratio Analysis'!E34 -> 43.17396 | E71: ='Ratio Analysis'!F34 -> 47.936824 | F71: ='Ratio Analysis'!G34 -> 49.844387 | G71: ='Ratio Analysis'!H34 -> 50.0229 | H71: ='Ratio Analysis'!I34 -> 42.420569 | ... K71: ='Ratio Analysis'!L34 -> 46.005493 | L71: =365/(L5/L70) -> 46.152487 | M71: =365/(M5/M70) -> 45.969862 | N71: =365/(N5/N70) -> 45.974661 | O71: =365/(O5/O70) -> 46.254731 | P71: =365/(P5/P70) -> 46.086522
A72: Average | B72: =AVERAGE(B71:K71) -> 46.152487 | C72: =AVERAGE(C71:L71) -> 45.969862 | D72: =AVERAGE(D71:M71) -> 45.974661 | E72: =AVERAGE(E71:N71) -> 46.254731 | F72: =AVERAGE(F71:O71) -> 46.086522
A74: ='Historical Financial Statement'!B51 -> Investments | B74: ='Historical Financial Statement'!C51 -> 3779 | C74: ='Historical Financial Statement'!D51 -> 3111 | D74: ='Historical Financial Statement'!E51 -> 2949 | E74: ='Historical Financial Statement'!F51 -> 1500 | F74: ='Historical Financial Statement'!G51 -> 2995 | G74: ='Historical Financial Statement'!H51 -> 4122 | H74: ='Historical Financial Statement'!I51 -> 3794 | ... K74: ='Historical Financial Statement'!L51 -> 8879 | L74: =L4*B76 -> 5890.533 | M74: =M4*C76 -> 5959.5745 | N74: =N4*D76 -> 6196.8551 | O74: =O4*E76 -> 6525.0657 | P74: =P4*F76 -> 7184.4095
A75: (%) | B75: =B74/B4 -> 0.1185011 | C75: =C74/C4 -> 0.090108617 | D75: =D74/D4 -> 0.077150481 | E75: =E74/E4 -> 0.038674745 | F75: =F74/F4 -> 0.065114358 | G75: =G74/G4 -> 0.080518821 | H75: =H74/H4 -> 0.064148519 | I75: =I74/I4 -> 0.090839935 | ... P75: =P74/P4 -> 0.08475127
A76: Avg | B76: =AVERAGE(B75:K75) -> 0.084544045 | C76: =AVERAGE(C75:L75) -> 0.08114834 | D76: =AVERAGE(D75:M75) -> 0.080252312 | E76: =AVERAGE(E75:N75) -> 0.080562495 | F76: =AVERAGE(F75:O75) -> 0.08475127
A78: ='Historical Financial Statement'!B82 -> Interest received | B78: ='Historical Financial Statement'!C82 -> 266 | C78: ='Historical Financial Statement'!D82 -> 229 | D78: ='Historical Financial Statement'!E82 -> 308 | E78: ='Historical Financial Statement'!F82 -> 359 | F78: ='Historical Financial Statement'!G82 -> 285 | G78: ='Historical Financial Statement'!H82 -> 171 | H78: ='Historical Financial Statement'!I82 -> 273 | ... K78: ='Historical Financial Statement'!L82 -> 431 | L78: =L74*B80 -> 625.14808 | M78: =M74*C80 -> 642.26774 | N78: =N74*D80 -> 686.13291 | O78: =O74*E80 -> 723.33376 | P78: =P74*F80 -> 790.57103
A79: (%) | B79: =B78/B70 -> 0.11261643 | C79: =C78/C70 -> 0.097075032 | D79: =D78/D70 -> 0.12716763 | E79: =E78/E70 -> 0.1361912 | F79: =F78/F70 -> 0.084244753 | G79: =G78/G70 -> 0.043958869 | H79: =H78/H70 -> 0.06772513 | I79: =I78/I70 -> 0.1093914 | ... P79: =P78/P70 -> 0.13340111
A80: Avg | B80: =AVERAGE(B79:K79) -> 0.10612759 | C80: =AVERAGE(C79:L79) -> 0.10777074 | D80: =AVERAGE(D79:M79) -> 0.11072276 | E80: =AVERAGE(E79:N79) -> 0.11085463 | F80: =AVERAGE(F79:O79) -> 0.11003981
A83: ='Historical Financial Statement'!B83 -> Dividends received | B83: ='Historical Financial Statement'!C83 -> 178 | C83: ='Historical Financial Statement'!D83 -> 190 | D83: ='Historical Financial Statement'!E83 -> 103 | E83: ='Historical Financial Statement'!F83 -> 96 | F83: ='Historical Financial Statement'!G83 -> 102 | G83: ='Historical Financial Statement'!H83 -> 131 | H83: ='Historical Financial Statement'!I83 -> 118 | ... K83: ='Historical Financial Statement'!L83 -> 230 | L83: =L74*B85 -> 234.86148 | M83: =M74*C85 -> 233.30462 | N83: =N74*D85 -> 229.00659 | O83: =O74*E85 -> 242.45912 | P83: =P74*F85 -> 247.67478
A84: (%) | B84: =B83/B74 -> 0.047102408 | C84: =C83/C74 -> 0.06107361 | D84: =D83/D74 -> 0.034927094 | E84: =E83/E74 -> 0.064 | F84: =F83/F74 -> 0.034056761 | G84: =G83/G74 -> 0.031780689 | H84: =H83/H74 -> 0.03110174 | I84: =I83/I74 -> 0.032040779 | ... P84: =P83/P74 -> 0.034473923
A85: Avg | B85: =AVERAGE(B84:K84) -> 0.039871006 | C85: =AVERAGE(C84:L84) -> 0.039147866 | D85: =AVERAGE(D84:M84) -> 0.036955292 | E85: =AVERAGE(E84:N84) -> 0.037158111 | F85: =AVERAGE(F84:O84) -> 0.034473923
A87: ='Historical Financial Statement'!B93 -> Interest paid fin | E87: ='Historical Financial Statement'!F93 -> -80 | F87: ='Historical Financial Statement'!G93 -> -86 | G87: ='Historical Financial Statement'!H93 -> -77 | H87: ='Historical Financial Statement'!I93 -> -76 | I87: ='Historical Financial Statement'!J93 -> -98 | J87: ='Historical Financial Statement'!K93 -> -118 | K87: ='Historical Financial Statement'!L93 -> -117 | L87: =K88*F90 -> -108.40056 | M87: =L88*G90 -> -61.79137 | N87: =M88*H90 -> -76.296974 | O87: =N88*I90 -> -86.463384 | P87: =O88*J90 -> -96.377118
A88: ='Historical Financial Statement'!B95 -> Financial liabilities | B88: ='Historical Financial Statement'!C95 -> 0 | C88: ='Historical Financial Statement'!D95 -> 0 | D88: ='Historical Financial Statement'!E95 -> 0 | E88: ='Historical Financial Statement'!F95 -> -352 | F88: ='Historical Financial Statement'!G95 -> -383 | G88: ='Historical Financial Statement'!H95 -> -388 | H88: ='Historical Financial Statement'!I95 -> -431 | ... P88: ='Historical Financial Statement'!Q95 -> -383.94513
A89: (%) | F89: =F87/E88 -> 0.24431818 | G89: =G87/F88 -> 0.20104439 | H89: =H87/G88 -> 0.19587629 | I89: =I87/H88 -> 0.22737819 | J89: =J87/I88 -> 0.29949239 | L89: =L87/K88 -> 0.23362189 | M89: =M87/L88 -> 0.23094781 | N89: =N87/M88 -> 0.23909219 | O89: =O87/N88 -> 0.24786007 | P89: =P87/P88 -> 0.25101795
A90: Avg | F90: =AVERAGE(F89:J89) -> 0.23362189 | G90: =AVERAGE(G89:K89) -> 0.23094781 | H90: =AVERAGE(H89:L89) -> 0.23909219 | I90: =AVERAGE(I89:M89) -> 0.24786007 | J90: =AVERAGE(J89:N89) -> 0.25078857

Sheet Ratio Analysis
B1: ="Ratio Analysis for "&'Data Sheet'!B1 -> Ratio Analysis for HINDUSTAN UNILEVER LTD
B2: ='Historical Financial Statement'!B2 -> Report Date | C2: ='Historical Financial Statement'!C2 -> 42825 | D2: ='Historical Financial Statement'!D2 -> 43190 | E2: ='Historical Financial Statement'!E2 -> 43555 | F2: ='Historical Financial Statement'!F2 -> 43921 | G2: ='Historical Financial Statement'!G2 -> 44286 | H2: ='Historical Financial Statement'!H2 -> 44651 | I2: ='Historical Financial Statement'!I2 -> 45016 | ... Q2: ='Historical Financial Statement'!Q2 -> 47937
B3: Profitability Ratios
B4: Gross Profit Margin | C4: ='Historical Financial Statement'!C9 -> 0.43653183 | D4: ='Historical Financial Statement'!D9 -> 0.45691528 | E4: ='Historical Financial Statement'!E9 -> 0.46431561 | F4: ='Historical Financial Statement'!F9 -> 0.48250612 | G4: ='Historical Financial Statement'!G9 -> 0.46140969 | H4: ='Historical Financial Statement'!H9 -> 0.4455492 | I4: ='Historical Financial Statement'!I9 -> 0.41356689 | J4: ='Historical Financial Statement'!J9 -> 0.45345549 | ... Q4: ='Historical Financial Statement'!Q9 -> 0.44632424
B5: EBITDA Margin | C5: ='Historical Financial Statement'!C14 -> 0.18962057 | D5: ='Historical Financial Statement'!D14 -> 0.21074584 | E5: ='Historical Financial Statement'!E14 -> 0.22595751 | F5: ='Historical Financial Statement'!F14 -> 0.24751837 | G5: ='Historical Financial Statement'!G14 -> 0.24619532 | H5: ='Historical Financial Statement'!H14 -> 0.24423261 | I5: ='Historical Financial Statement'!I14 -> 0.2304883 | J5: ='Historical Financial Statement'!J14 -> 0.2346657 | ... Q5: ='Historical Financial Statement'!Q14 -> 0.24069735
B6: EBIT Margin | C6: ='Historical Financial Statement'!C18 -> 0.17720288 | D6: ='Historical Financial Statement'!D18 -> 0.1969008 | E6: ='Historical Financial Statement'!E18 -> 0.21224885 | F6: ='Historical Financial Statement'!F18 -> 0.22333376 | G6: ='Historical Financial Statement'!G18 -> 0.22419341 | H6: ='Historical Financial Statement'!H18 -> 0.22421034 | I6: ='Historical Financial Statement'!I18 -> 0.21307318 | J6: ='Historical Financial Statement'!J18 -> 0.21652417 | ... Q6: ='Historical Financial Statement'!Q18 -> 0.22672268
B7: Net Profit Margin | C7: ='Historical Financial Statement'!C27 -> 0.14079649 | D7: ='Historical Financial Statement'!D27 -> 0.15168718 | E7: ='Historical Financial Statement'!E27 -> 0.15791126 | F7: ='Historical Financial Statement'!F27 -> 0.17372696 | G7: ='Historical Financial Statement'!G27 -> 0.17292808 | H7: ='Historical Financial Statement'!H27 -> 0.17225011 | I7: ='Historical Financial Statement'!I27 -> 0.16843636 | J7: ='Historical Financial Statement'!J27 -> 0.16725926 | ... Q7: ='Historical Financial Statement'!Q27 -> 0.20470813
B8: Return On Assests | C8: ='Historical Financial Statement'!C26/'Historical Financial Statement'!C61 -> 0.30438614 | D8: ='Historical Financial Statement'!D26/'Historical Financial Statement'!D61 -> 0.30538224 | E8: ='Historical Financial Statement'!E26/'Historical Financial Statement'!E61 -> 0.33786734 | F8: ='Historical Financial Statement'!F26/'Historical Financial Statement'!F61 -> 0.34374043 | G8: ='Historical Financial Statement'!G26/'Historical Financial Statement'!G61 -> 0.11677139 | H8: ='Historical Financial Statement'!H26/'Historical Financial Statement'!H61 -> 0.12644651 | I8: ='Historical Financial Statement'!I26/'Historical Financial Statement'!I61 -> 0.13869822 | J8: ='Historical Financial Statement'!J26/'Historical Financial Statement'!J61 -> 0.13122113 | ... Q8: ='Historical Financial Statement'!Q26/'Historical Financial Statement'!Q61 -> 0.22291617
B9: Return On Equity | C9: ='Historical Financial Statement'!C26/SUM('Historical Financial Statement'!C31:C32) -> 0.69183359 | D9: ='Historical Financial Statement'!D26/SUM('Historical Financial Statement'!D31:D32) -> 0.74021201 | E9: ='Historical Financial Statement'!E26/SUM('Historical Financial Statement'!E31:E32) -> 0.78809244 | F9: ='Historical Financial Statement'!F26/SUM('Historical Financial Statement'!F31:F32) -> 0.83899888 | G9: ='Historical Financial Statement'!G26/SUM('Historical Financial Statement'!G31:G32) -> 0.16768563 | H9: ='Historical Financial Statement'!H26/SUM('Historical Financial Statement'!H31:H32) -> 0.18084495 | I9: ='Historical Financial Statement'!I26/SUM('Historical Financial Statement'!I31:I32) -> 0.19836323 | J9: ='Historical Financial Statement'!J26/SUM('Historical Financial Statement'!J31:J32) -> 0.19841877 | ... Q9: ='Historical Financial Statement'!Q26/SUM('Historical Financial Statement'!Q31:Q32) -> 0.29886044
B11: Solvency Ratios
B12: D/E Ratio | C12: ='Historical Financial Statement'!C41/SUM('Historical Financial Statement'!C31:C32) -> 0 | D12: ='Historical Financial Statement'!D41/SUM('Historical Financial Statement'!D31:D32) -> 0 | E12: ='Historical Financial Statement'!E41/SUM('Historical Financial Statement'!E31:E32) -> 0 | F12: ='Historical Financial Statement'!F41/SUM('Historical Financial Statement'!F31:F32) -> 0 | G12: ='Historical Financial Statement'!G41/SUM('Historical Financial Statement'!G31:G32) -> 0.019880255 | H12: ='Historical Financial Statement'!H41/SUM('Historical Financial Statement'!H31:H32) -> 0.019913864 | I12: ='Historical Financial Statement'!I41/SUM('Historical Financial Statement'!I31:I32) -> 0.020688557 | J12: ='Historical Financial Statement'!J41/SUM('Historical Financial Statement'!J31:J32) -> 0.026955447 | ... Q12: ='Historical Financial Statement'!Q41/SUM('Historical Financial Statement'!Q31:Q32) -> 0.022819407
B13: Debt Ratio | C13: ='Historical Financial Statement'!C41/'Historical Financial Statement'!C61 -> 0 | D13: ='Historical Financial Statement'!D41/'Historical Financial Statement'!D61 -> 0 | E13: ='Historical Financial Statement'!E41/'Historical Financial Statement'!E61 -> 0 | F13: ='Historical Financial Statement'!F41/'Historical Financial Statement'!F61 -> 0 | G13: ='Historical Financial Statement'!G41/'Historical Financial Statement'!G61 -> 0.013844031 | H13: ='Historical Financial Statement'!H41/'Historical Financial Statement'!H61 -> 0.013923742 | I13: ='Historical Financial Statement'!I41/'Historical Financial Statement'!I61 -> 0.014465715 | J13: ='Historical Financial Statement'!J41/'Historical Financial Statement'!J61 -> 0.017826561 | ... Q13: ='Historical Financial Statement'!Q41/'Historical Financial Statement'!Q61 -> 0.017020703
B14: Interest Coverage Ratio | C14: ='Historical Financial Statement'!C17/'Historical Financial Statement'!C20 -> 256.86364 | D14: ='Historical Financial Statement'!D17/'Historical Financial Statement'!D20 -> 339.9 | E14: ='Historical Financial Statement'!E17/'Historical Financial Statement'!E20 -> 289.75 | F14: ='Historical Financial Statement'!F17/'Historical Financial Statement'!F20 -> 81.716981 | G14: ='Historical Financial Statement'!G17/'Historical Financial Statement'!G20 -> 95.481481 | H14: ='Historical Financial Statement'!H17/'Historical Financial Statement'!H20 -> 117.12245 | I14: ='Historical Financial Statement'!I17/'Historical Financial Statement'!I20 -> 124.77228 | J14: ='Historical Financial Statement'!J17/'Historical Financial Statement'!J20 -> 43.354305 | ... Q14: ='Historical Financial Statement'!Q17/'Historical Financial Statement'!Q20 -> 68.88523
B16: Efficency Ratios
B17: Assets Turnover Ratio | C17: ='Historical Financial Statement'!C5/'Historical Financial Statement'!C61 -> 2.1618873 | D17: ='Historical Financial Statement'!D5/'Historical Financial Statement'!D61 -> 2.0132369 | E17: ='Historical Financial Statement'!E5/'Historical Financial Statement'!E61 -> 2.1396026 | F17: ='Historical Financial Statement'!F5/'Historical Financial Statement'!F61 -> 1.9786246 | G17: ='Historical Financial Statement'!G5/'Historical Financial Statement'!G61 -> 0.67525985 | H17: ='Historical Financial Statement'!H5/'Historical Financial Statement'!H61 -> 0.73408664 | I17: ='Historical Financial Statement'!I5/'Historical Financial Statement'!I61 -> 0.82344588 | J17: ='Historical Financial Statement'!J5/'Historical Financial Statement'!J61 -> 0.78453734 | ... Q17: ='Historical Financial Statement'!Q5/'Historical Financial Statement'!Q61 -> 1.0889464
B18: Inventory Turnover Ratio | C18: ='Historical Financial Statement'!C7/'Historical Financial Statement'!C57 -> 7.607536 | D18: ='Historical Financial Statement'!D7/'Historical Financial Statement'!D57 -> 7.9482832 | E18: ='Historical Financial Statement'!E7/'Historical Financial Statement'!E57 -> 8.4541701 | F18: ='Historical Financial Statement'!F7/'Historical Financial Statement'!F57 -> 7.6141882 | G18: ='Historical Financial Statement'!G7/'Historical Financial Statement'!G57 -> 7.3227904 | H18: ='Historical Financial Statement'!H7/'Historical Financial Statement'!H57 -> 7.2966581 | I18: ='Historical Financial Statement'!I7/'Historical Financial Statement'!I57 -> 8.6043165 | J18: ='Historical Financial Statement'!J7/'Historical Financial Statement'!J57 -> 8.6697272 | ... Q18: ='Historical Financial Statement'!Q7/'Historical Financial Statement'!Q57 -> 7.919886
B19: Receivable Turnover Ratio | C19: ='Historical Financial Statement'!C5/'Historical Financial Statement'!C56 -> 34.364224 | D19: ='Historical Financial Statement'!D5/'Historical Financial Statement'!D56 -> 30.100262 | E19: ='Historical Financial Statement'!E5/'Historical Financial Statement'!E56 -> 22.847579 | F19: ='Historical Financial Statement'!F5/'Historical Financial Statement'!F56 -> 37.07935 | G19: ='Historical Financial Statement'!G5/'Historical Financial Statement'!G56 -> 27.910194 | H19: ='Historical Financial Statement'!H5/'Historical Financial Statement'!H56 -> 26.497412 | I19: ='Historical Financial Statement'!I5/'Historical Financial Statement'!I56 -> 21.624863 | J19: ='Historical Financial Statement'!J5/'Historical Financial Statement'!J56 -> 22.479182 | ... Q19: ='Historical Financial Statement'!Q5/'Historical Financial Statement'!Q56 -> 22.846473
B20: Payable Turnover Ratio | C20: ='Historical Financial Statement'!C7/'Historical Financial Statement'!C36 -> 2.9918415 | D20: ='Historical Financial Statement'!D7/'Historical Financial Statement'!D36 -> 2.6736062 | E20: ='Historical Financial Statement'!E7/'Historical Financial Statement'!E36 -> 2.896181 | F20: ='Historical Financial Statement'!F7/'Historical Financial Statement'!F36 -> 2.7126639 | G20: ='Historical Financial Statement'!G7/'Historical Financial Statement'!G36 -> 2.871566 | H20: ='Historical Financial Statement'!H7/'Historical Financial Statement'!H36 -> 3.2021661 | I20: ='Historical Financial Statement'!I7/'Historical Financial Statement'!I36 -> 3.6933234 | J20: ='Historical Financial Statement'!J7/'Historical Financial Statement'!J36 -> 3.2567008 | ... Q20: ='Historical Financial Statement'!Q7/'Historical Financial Statement'!Q36 -> 3.0468811
B21: Fixed Assets Turnover Ratio | C21: ='Historical Financial Statement'!C5/'Historical Financial Statement'!C49 -> 7.9249503 | D21: ='Historical Financial Statement'!D5/'Historical Financial Statement'!D49 -> 8.3353452 | E21: ='Historical Financial Statement'!E5/'Historical Financial Statement'!E49 -> 8.8012894 | F21: ='Historical Financial Statement'!F5/'Historical Financial Statement'!F49 -> 7.6710839 | G21: ='Historical Financial Statement'!G5/'Historical Financial Statement'!G49 -> 0.90140514 | H21: ='Historical Financial Statement'!H5/'Historical Financial Statement'!H49 -> 1.0031156 | I21: ='Historical Financial Statement'!I5/'Historical Financial Statement'!I49 -> 1.1505496 | J21: ='Historical Financial Statement'!J5/'Historical Financial Statement'!J49 -> 1.1544512 | ... Q21: ='Historical Financial Statement'!Q5/'Historical Financial Statement'!Q49 -> 1.4680242
B23: Liquidity Ratios
B24: Current Ratio | C24: ='Historical Financial Statement'!C59/'Historical Financial Statement'!C38 -> 0.81649111 | D24: ='Historical Financial Statement'!D59/'Historical Financial Statement'!D38 -> 0.97325976 | E24: ='Historical Financial Statement'!E59/'Historical Financial Statement'!E38 -> 1.0948094 | F24: ='Historical Financial Statement'!F59/'Historical Financial Statement'!F38 -> 1.1517278 | G24: ='Historical Financial Statement'!G59/'Historical Financial Statement'!G38 -> 1.0724771 | H24: ='Historical Financial Statement'!H59/'Historical Financial Statement'!H38 -> 1.0515763 | I24: ='Historical Financial Statement'!I59/'Historical Financial Statement'!I38 -> 1.1805424 | J24: ='Historical Financial Statement'!J59/'Historical Financial Statement'!J38 -> 1.340041 | ... Q24: ='Historical Financial Statement'!Q59/'Historical Financial Statement'!Q38 -> 0.28711999
B25: Quick Ratio | C25: =('Historical Financial Statement'!C59-'Historical Financial Statement'!C57)/'Historical Financial Statement'!C38 -> 0.42774852 | D25: =('Historical Financial Statement'!D59-'Historical Financial Statement'!D57)/'Historical Financial Statement'!D38 -> 0.63950198 | E25: =('Historical Financial Statement'!E59-'Historical Financial Statement'!E57)/'Historical Financial Statement'!E38 -> 0.7541145 | F25: =('Historical Financial Statement'!F59-'Historical Financial Statement'!F57)/'Historical Financial Statement'!F38 -> 0.80272739 | G25: =('Historical Financial Statement'!G59-'Historical Financial Statement'!G57)/'Historical Financial Statement'!G38 -> 0.68451835 | H25: =('Historical Financial Statement'!H59-'Historical Financial Statement'!H57)/'Historical Financial Statement'!H38 -> 0.61824663 | I25: =('Historical Financial Statement'!I59-'Historical Financial Statement'!I57)/'Historical Financial Statement'!I38 -> 0.75519679 | J25: =('Historical Financial Statement'!J59-'Historical Financial Statement'!J57)/'Historical Financial Statement'!J38 -> 0.96766631 | ... Q25: =('Historical Financial Statement'!Q59-'Historical Financial Statement'!Q57)/'Historical Financial Statement'!Q38 -> -0.094779333
B26: Cash Ratio | C26: ='Historical Financial Statement'!C58/'Historical Financial Statement'!C38 -> 0.27501646 | D26: ='Historical Financial Statement'!D58/'Historical Financial Statement'!D38 -> 0.47722128 | E26: ='Historical Financial Statement'!E58/'Historical Financial Statement'!E38 -> 0.51877901 | F26: ='Historical Financial Statement'!F58/'Historical Financial Statement'!F38 -> 0.66423938 | G26: ='Historical Financial Statement'!G58/'Historical Financial Statement'!G38 -> 0.49552752 | H26: ='Historical Financial Statement'!H58/'Historical Financial Statement'!H38 -> 0.40302997 | I26: ='Historical Financial Statement'!I58/'Historical Financial Statement'!I38 -> 0.46660336 | J26: ='Historical Financial Statement'!J58/'Historical Financial Statement'!J38 -> 0.70489401 | ... Q26: ='Historical Financial Statement'!Q58/'Historical Financial Statement'!Q38 -> -0.3338868
B28: Market Ratios
B29: Eairning Per Share | C29: ='Historical Financial Statement'!C26/'Data Sheet'!B93 -> 20.745738 | D29: ='Historical Financial Statement'!D26/'Data Sheet'!C93 -> 24.194964 | E29: ='Historical Financial Statement'!E26/'Data Sheet'!D93 -> 27.883771 | F29: ='Historical Financial Statement'!F26/'Data Sheet'!E93 -> 31.125277 | G29: ='Historical Financial Statement'!G26/'Data Sheet'!F93 -> 33.852571 | H29: ='Historical Financial Statement'!H26/'Data Sheet'!G93 -> 37.529792 | I29: ='Historical Financial Statement'!I26/'Data Sheet'!H93 -> 42.398706 | J29: ='Historical Financial Statement'!J26/'Data Sheet'!I93 -> 43.045625 | ... L29: ='Historical Financial Statement'!L26/'Data Sheet'!K93 -> 65.657984 | M29: =_xlfn.FORECAST.LINEAR(M$2,$C29:$L29,$C$2:$L$2) -> 59.343907 | N29: =_xlfn.FORECAST.LINEAR(N$2,$C29:$L29,$C$2:$L$2) -> 63.372869 | O29: =_xlfn.FORECAST.LINEAR(O$2,$C29:$L29,$C$2:$L$2) -> 67.401832 | P29: =_xlfn.FORECAST.LINEAR(P$2,$C29:$L29,$C$2:$L$2) -> 71.430794 | Q29: =_xlfn.FORECAST.LINEAR(Q$2,$C29:$L29,$C$2:$L$2) -> 75.459756
B30: P/E Ratio | C30: ='Data Sheet'!B90/'Ratio Analysis'!C29 -> 42.062134 | D30: ='Data Sheet'!C90/'Ratio Analysis'!D29 -> 52.742793 | E30: ='Data Sheet'!D90/'Ratio Analysis'!E29 -> 58.583539 | F30: ='Data Sheet'!E90/'Ratio Analysis'!F29 -> 70.67664 | G30: ='Data Sheet'!F90/'Ratio Analysis'!G29 -> 68.742785 | H30: ='Data Sheet'!G90/'Ratio Analysis'!H29 -> 52.243828 | I30: ='Data Sheet'!H90/'Ratio Analysis'!I29 -> 57.79516 | J30: ='Data Sheet'!I90/'Ratio Analysis'!J29 -> 50.345186 | ... L30: ='Data Sheet'!K90/'Ratio Analysis'!L29 -> 31.301601 | M30: =_xlfn.FORECAST.LINEAR(M$2,$C30:$L30,$C$2:$L$2) -> 45.613225 | N30: =_xlfn.FORECAST.LINEAR(N$2,$C30:$L30,$C$2:$L$2) -> 44.230575 | O30: =_xlfn.FORECAST.LINEAR(O$2,$C30:$L30,$C$2:$L$2) -> 42.847925 | P30: =_xlfn.FORECAST.LINEAR(P$2,$C30:$L30,$C$2:$L$2) -> 41.465275 | Q30: =_xlfn.FORECAST.LINEAR(Q$2,$C30:$L30,$C$2:$L$2) -> 40.082625
B31: Book Value Per Share | C31: =SUM('Historical Financial Statement'!C31:C32)/'Data Sheet'!B93 -> 29.986601 | D31: =SUM('Historical Financial Statement'!D31:D32)/'Data Sheet'!C93 -> 32.686533 | E31: =SUM('Historical Financial Statement'!E31:E32)/'Data Sheet'!D93 -> 35.381346 | F31: =SUM('Historical Financial Statement'!F31:F32)/'Data Sheet'!E93 -> 37.098115 | G31: =SUM('Historical Financial Statement'!G31:G32)/'Data Sheet'!F93 -> 201.88117 | H31: =SUM('Historical Financial Statement'!H31:H32)/'Data Sheet'!G93 -> 207.52469 | I31: =SUM('Historical Financial Statement'!I31:I32)/'Data Sheet'!H93 -> 213.74276 | J31: =SUM('Historical Financial Statement'!J31:J32)/'Data Sheet'!I93 -> 216.94331 | ... L31: =SUM('Historical Financial Statement'!L31:L32)/'Data Sheet'!K93 -> 209.49523 | M31: =_xlfn.FORECAST.LINEAR(M$2,$C31:$L31,$C$2:$L$2) -> 282.5149 | N31: =_xlfn.FORECAST.LINEAR(N$2,$C31:$L31,$C$2:$L$2) -> 308.52398 | O31: =_xlfn.FORECAST.LINEAR(O$2,$C31:$L31,$C$2:$L$2) -> 334.53306 | P31: =_xlfn.FORECAST.LINEAR(P$2,$C31:$L31,$C$2:$L$2) -> 360.54214 | Q31: =_xlfn.FORECAST.LINEAR(Q$2,$C31:$L31,$C$2:$L$2) -> 386.55122
B33: Operating Cycle Ratios (in Days)
B34: Inventory Days | C34: =365/C18 -> 47.978741 | D34: =365/D18 -> 45.921867 | E34: =365/E18 -> 43.17396 | F34: =365/F18 -> 47.936824 | G34: =365/G18 -> 49.844387 | H34: =365/H18 -> 50.0229 | I34: =365/I18 -> 42.420569 | J34: =365/J18 -> 42.100517 | ... L34: =365/L18 -> 46.005493 | M34: =Calculation!L71 -> 46.152487 | N34: =Calculation!M71 -> 45.969862 | O34: =Calculation!N71 -> 45.974661 | P34: =Calculation!O71 -> 46.254731 | Q34: =Calculation!P71 -> 46.086522
B35: Receivable Days | C35: =365/C19 -> 10.621511 | D35: =365/D19 -> 12.12614 | E35: =365/E19 -> 15.975434 | F35: =365/F19 -> 9.843754 | G35: =365/G19 -> 13.077659 | H35: =365/H19 -> 13.77493 | I35: =365/I19 -> 16.87872 | J35: =365/J19 -> 16.237246 | ... L35: =365/L19 -> 17.886325 | M35: =Calculation!L67 -> 14.752317 | N35: =Calculation!M67 -> 15.165397 | O35: =Calculation!N67 -> 15.469323 | P35: =Calculation!O67 -> 15.418712 | Q35: =Calculation!P67 -> 15.976208
B36: Payable Days | C36: =365/C20 -> 121.99844 | D36: =365/D20 -> 136.51973 | E36: =365/E20 -> 126.02803 | F36: =365/F20 -> 134.55408 | G36: =365/G20 -> 127.10834 | H36: =365/H20 -> 113.98534 | I36: =365/I20 -> 98.826981 | J36: =365/J20 -> 112.07661 | ... L36: =365/L20 -> 135.53934 | M36: =Calculation!L47 -> 122.85363 | N36: =Calculation!M47 -> 122.93915 | O36: =Calculation!N47 -> 121.5811 | P36: =Calculation!O47 -> 121.1364 | Q36: =Calculation!P47 -> 119.79463
B38: Cash Conversion Days | C38: =SUM(C34:C35)-C36 -> -63.398189 | D38: =SUM(D34:D35)-D36 -> -78.471726 | E38: =SUM(E34:E35)-E36 -> -66.878639 | F38: =SUM(F34:F35)-F36 -> -76.773505 | G38: =SUM(G34:G35)-G36 -> -64.186298 | H38: =SUM(H34:H35)-H36 -> -50.187513 | I38: =SUM(I34:I35)-I36 -> -39.527692 | J38: =SUM(J34:J35)-J36 -> -53.738851 | ... Q38: =SUM(Q34:Q35)-Q36 -> -57.731903
B40: Market Prospect Ratios
B41: Dividend Payout Ratio | C41: ='Data Sheet'!B31/'Data Sheet'!B30 -> 0.81781737 | D41: ='Data Sheet'!C31/'Data Sheet'!C30 -> 0.82489975 | E41: ='Data Sheet'!D31/'Data Sheet'!D30 -> 0.78727634 | F41: ='Data Sheet'!E31/'Data Sheet'!E30 -> 0.80142476 | G41: ='Data Sheet'!F31/'Data Sheet'!F30 -> 1.1965678 | H41: ='Data Sheet'!G31/'Data Sheet'!G30 -> 0.90610116 | I41: ='Data Sheet'!H31/'Data Sheet'!H30 -> 0.91999598 | J41: ='Data Sheet'!I31/'Data Sheet'!I30 -> 0.97587502 | ... L41: ='Data Sheet'!K31/'Data Sheet'!K30 -> 0.62455435 | M41: =_xlfn.FORECAST.LINEAR(M$2,C$41:L$41,$C$2:$L$2) -> 0.95866317 | N41: =_xlfn.FORECAST.LINEAR(N$2,D$41:M$41,$C$2:$L$2) -> 0.96622027 | O41: =_xlfn.FORECAST.LINEAR(O$2,E$41:N$41,$C$2:$L$2) -> 0.96236813 | P41: =_xlfn.FORECAST.LINEAR(P$2,F$41:O$41,$C$2:$L$2) -> 0.91766111 | Q41: =_xlfn.FORECAST.LINEAR(Q$2,G$41:P$41,$C$2:$L$2) -> 0.81699167
B42: Retention Ratio | C42: =1-C41 -> 0.18218263 | D42: =1-D41 -> 0.17510025 | E42: =1-E41 -> 0.21272366 | F42: =1-F41 -> 0.19857524 | G42: =1-G41 -> -0.19656776 | H42: =1-H41 -> 0.093898843 | I42: =1-I41 -> 0.080004015 | J42: =1-J41 -> 0.024124975 | ... Q42: =1-Q41 -> 0.18300833
B44: Sustainable Growth Rate | C44: =C42*C9 -> 0.12604006 | D44: =D42*D9 -> 0.12961131 | E44: =E42*E9 -> 0.16764591 | F44: =F42*F9 -> 0.16660441 | G44: =G42*G9 -> -0.032961589 | H44: =H42*H9 -> 0.016981132 | I44: =I42*I9 -> 0.015869855 | J44: =J42*J9 -> 0.0047868479 | ... Q44: =Q42*Q9 -> 0.054693951

Sheet DCF Model
B1: ="DCF Model for "&'Data Sheet'!B1 -> DCF Model for HINDUSTAN UNILEVER LTD
B2: ="WACC Calculation for "&'Data Sheet'!B1 -> WACC Calculation for HINDUSTAN UNILEVER LTD | E2: ="Discount Cash-Flow for "&'Data Sheet'!B1 -> Discount Cash-Flow for HINDUSTAN UNILEVER LTD
B3: Equity | C3: 426802 | F3: 1 | G3: 2 | H3: 3 | I3: 4 | J3: 5 | K3: 6 | L3: 7 | M3: 8 | N3: 9 | O3: 10
B4: Debt | C4: 1325 | E4: EBIT | F4: ='Historical Financial Statement'!C17 -> 5651 | G4: ='Historical Financial Statement'!D17 -> 6798 | H4: ='Historical Financial Statement'!E17 -> 8113 | I4: ='Historical Financial Statement'!F17 -> 8662 | J4: ='Historical Financial Statement'!G17 -> 10312 | K4: ='Historical Financial Statement'!H17 -> 11478 | L4: ='Historical Financial Statement'!I17 -> 12602 | M4: ='Historical Financial Statement'!J17 -> 13093 | ... O4: ='Historical Financial Statement'!L17 -> 13278
B5: Weightage of Equity | C5: =C3/SUM(C3:C4) -> 0.99690512 | E5: Tax Rate | F5: =$C7 -> 0.16552172 | G5: =$C7 -> 0.16552172 | H5: =$C7 -> 0.16552172 | I5: =$C7 -> 0.16552172 | J5: =$C7 -> 0.16552172 | K5: =$C7 -> 0.16552172 | L5: =$C7 -> 0.16552172 | M5: =$C7 -> 0.16552172 | ... O5: =$C7 -> 0.16552172
B6: Weightage of Debt | C6: =C4/SUM(C3:C4) -> 0.0030948761 | E6: Depreciation | F6: ='Historical Financial Statement'!C16 -> 396 | G6: ='Historical Financial Statement'!D16 -> 478 | H6: ='Historical Financial Statement'!E16 -> 524 | I6: ='Historical Financial Statement'!F16 -> 938 | J6: ='Historical Financial Statement'!G16 -> 1012 | K6: ='Historical Financial Statement'!H16 -> 1025 | L6: ='Historical Financial Statement'!I16 -> 1030 | M6: ='Historical Financial Statement'!J16 -> 1097 | ... O6: ='Historical Financial Statement'!L16 -> 1186
B7: Tax | C7: ='Historical Financial Statement'!L25/'Historical Financial Statement'!L22 -> 0.16552172 | E7: CapEx | F7: ='Historical Financial Statement'!C78 -> -1024 | G7: ='Historical Financial Statement'!D78 -> -853 | H7: ='Historical Financial Statement'!E78 -> -728 | I7: ='Historical Financial Statement'!F78 -> -765 | J7: ='Historical Financial Statement'!G78 -> -4051 | K7: ='Historical Financial Statement'!H78 -> -919 | L7: ='Historical Financial Statement'!I78 -> -1041 | M7: ='Historical Financial Statement'!J78 -> -1318 | ... O7: ='Historical Financial Statement'!L78 -> -1274
B8: Time Period | C8: 10 | E8: Non-Cash WC | F8: =SUM('Historical Financial Statement'!C57,'Historical Financial Statement'!C56)-'Historical Financial Statement'!C36 -> -2716 | G8: =SUM('Historical Financial Statement'!D57,'Historical Financial Statement'!D56)-'Historical Financial Statement'!D36 -> -3507 | H8: =SUM('Historical Financial Statement'!E57,'Historical Financial Statement'!E56)-'Historical Financial Statement'!E36 -> -2975 | I8: =SUM('Historical Financial Statement'!F57,'Historical Financial Statement'!F56)-'Historical Financial Statement'!F36 -> -3717 | J8: =SUM('Historical Financial Statement'!G57,'Historical Financial Statement'!G56)-'Historical Financial Statement'!G36 -> -3596 | K8: =SUM('Historical Financial Statement'!H57,'Historical Financial Statement'!H56)-'Historical Financial Statement'!H36 -> -3042 | L8: =SUM('Historical Financial Statement'!I57,'Historical Financial Statement'!I56)-'Historical Financial Statement'!I36 -> -2625 | M8: =SUM('Historical Financial Statement'!J57,'Historical Financial Statement'!J56)-'Historical Financial Statement'!J36 -> -3646 | ... O8: =SUM('Historical Financial Statement'!L57,'Historical Financial Statement'!L56)-'Historical Financial Statement'!L36 -> -5493
B9: Fixed Market Return | C9: 0.0729 | E9: FCF | F9: =F4*(1-F5)+F6-F7-F8 -> 8851.6368 | G9: =G4*(1-G5)+G6-G7-G8 -> 10510.783 | H9: =H4*(1-H5)+H6-H7-H8 -> 10997.122 | I9: =I4*(1-I5)+I6-I7-I8 -> 12648.251 | J9: =J4*(1-J5)+J6-J7-J8 -> 17264.14 | K9: =K4*(1-K5)+K6-K7-K8 -> 14564.142 | L9: =L4*(1-L5)+L6-L7-L8 -> 15212.095 | M9: =M4*(1-M5)+M6-M7-M8 -> 16986.824 | ... O9: =O4*(1-O5)+O6-O7-O8 -> 19033.203
B10: Expected Market Return | C10: =_xlfn.RRI(C8,'BETA Calculation'!G525,'BETA Calculation'!G4) -> 0.099098128
B11: Cost of Debt | C11: =('Historical Financial Statement'!L20/'DCF Model'!C4)*(1-'DCF Model'!C7) -> 0.22861556 | E11: Perpetual Growth Rate | G11: 0.06
B12: Cost of Equity | C12: =C9+C13*(C10-C9) -> 0.086463244 | E12: WACC | G12: =C16 -> 0.086903188
B13: Beta(L) | C13: ='BETA Calculation'!L8 -> 0.51771806 | E13: Terminal Value | G13: =O9*(1+G11)/(G12-G11) -> 749918.36
E15: Discounted Factor | G15: =1/(1+$G12)^F3 -> 0.92004514 | H15: =1/(1+$G12)^G3 -> 0.84648307 | I15: =1/(1+$G12)^H3 -> 0.77880263 | J15: =1/(1+$G12)^I3 -> 0.71653358 | K15: =1/(1+$G12)^J3 -> 0.65924324 | L15: =1/(1+$G12)^K3 -> 0.60653354 | M15: =1/(1+$G12)^L3 -> 0.55803824 | N15: =1/(1+$G12)^M3 -> 0.51342037 | ... P15: =1/(1+$G12)^O3 -> 0.43460165
B16: WACC | C16: =(C5*C12)+(C6*C11) -> 0.086903188 | E16: PV of FCF | G16: =F9*G15 -> 8143.9054 | H16: =G9*H15 -> 8897.2001 | I16: =H9*I15 -> 8564.5878 | J16: =I9*J15 -> 9062.8965 | K16: =J9*K15 -> 11381.268 | L16: =K9*L15 -> 8833.6405 | M16: =L9*M15 -> 8488.9309 | N16: =M9*N15 -> 8721.3816 | ... P16: =O9*P15 -> 8271.8613
E17: PV of Terminal Value | G17: =G13*P15 -> 325915.76
B19: India’s real GDP growth rate with Q1 FY 2026‑27 showing 7.8% growth | E19: Enterprise Value | G19: =SUM(G16:P16,G17) -> 414087.15
B20: India’s nominal GDP grew by 10.3% year‑on‑year in Q1 FY 2026‑27 | E20: Net Debt | G20: ='Historical Financial Statement'!L41-'Historical Financial Statement'!L58 -> -1505
B21: India’s annual inflation rate stood at 4.96% (YoY) | E21: Market Captalization | G21: =G19-G20 -> 415592.15
E22: No. of Share | G22: ='Data Sheet'!K93 -> 234.96
E24: Share Price | G24: =G21/G22 -> 1768.7783

Sheet BETA Calculation
B1: ="BETA(L) Calculation for "&'Data Sheet'!B1 -> BETA(L) Calculation for HINDUSTAN UNILEVER LTD
B2: ='Data Sheet'!B1 -> HINDUSTAN UNILEVER LTD | F2: NIFTY-50
B3: Date | C3: Price | D3: Return | F3: Date | G3: Price | H3: Return
B4: 46306 | C4: 1820.7 | D4: =IFERROR((C4/C5)-1,0) -> -0.019389239 | F4: 46306 | G4: 22363.35 | H4: =IFERROR((G4/G5)-1,0) -> -0.0069758819 | K4: BETA(L) Calculation
B5: 46299 | C5: 1856.7 | D5: =IFERROR((C5/C6)-1,0) -> 0.01127451 | F5: 46299 | G5: 22520.45 | H5: =IFERROR((G5/G6)-1,0) -> 0.0043930167 | K5: Correlation between HUL & NIFTY-50 | L5: =CORREL(D4:D525,H4:H525) -> 0.39201462
B6: 46292 | C6: 1836 | D6: =IFERROR((C6/C7)-1,0) -> -0.055020845 | F6: 46292 | G6: 22421.95 | H6: =IFERROR((G6/G7)-1,0) -> -0.031051619 | K6: Standard Deviation of HUL | L6: =_xlfn.STDEV.S(D4:D525) -> 0.027986552
B7: 46285 | C7: 1942.9 | D7: =IFERROR((C7/C8)-1,0) -> 0.0056418219 | F7: 46285 | G7: 23140.5 | H7: =IFERROR((G7/G8)-1,0) -> -0.0088193469 | K7: Standard Deviation of Nifty-50 | L7: =_xlfn.STDEV.S(H4:H525) -> 0.021191336
B8: 46278 | C8: 1932 | D8: =IFERROR((C8/C9)-1,0) -> 0.0025947068 | F8: 46278 | G8: 23346.4 | H8: =IFERROR((G8/G9)-1,0) -> -0.0022095811 | K8: BETA(L) | L8: =L5*(L6/L7) -> 0.51771806
B9: 46271 | C9: 1927 | D9: =IFERROR((C9/C10)-1,0) -> -0.023512719 | F9: 46271 | G9: 23398.1 | H9: =IFERROR((G9/G10)-1,0) -> -0.020905778 | K9: BETA(UL) | L9: =L8/(1+('DCF Model'!C4/'DCF Model'!C3)*(1-'DCF Model'!C7)) -> 0.51638032
B10: 46264 | C10: 1973.4 | D10: =IFERROR((C10/C11)-1,0) -> -0.018404298 | F10: 46264 | G10: 23897.7 | H10: =IFERROR((G10/G11)-1,0) -> -0.011497106 | K10: BETA(L) Re-check | L10: =SLOPE(D4:D525,H4:H525) -> 0.51771806
B11: 46257 | C11: 2010.4 | D11: =IFERROR((C11/C12)-1,0) -> -0.0022828784 | F11: 46257 | G11: 24175.65 | H11: =IFERROR((G11/G12)-1,0) -> -0.003148194
B12: 46250 | C12: 2015 | D12: =IFERROR((C12/C13)-1,0) -> -0.029850746 | F12: 46250 | G12: 24252 | H12: =IFERROR((G12/G13)-1,0) -> -0.0046786506
B13: 46243 | C13: 2077 | D13: =IFERROR((C13/C14)-1,0) -> -0.0090648855 | F13: 46243 | G13: 24366 | H13: =IFERROR((G13/G14)-1,0) -> -0.008329043
B14: 46236 | C14: 2096 | D14: =IFERROR((C14/C15)-1,0) -> -0.0025222481 | F14: 46236 | G14: 24570.65 | H14: =IFERROR((G14/G15)-1,0) -> 0.0076711396
B15: 46229 | C15: 2101.3 | D15: =IFERROR((C15/C16)-1,0) -> -0.02037296 | F15: 46229 | G15: 24383.6 | H15: =IFERROR((G15/G16)-1,0) -> 0.02592411
B16: 46222 | C16: 2145 | D16: =IFERROR((C16/C17)-1,0) -> 0.00055975371 | F16: 46222 | G16: 23767.45 | H16: =IFERROR((G16/G17)-1,0) -> -0.02329428
B17: 46215 | C17: 2143.8 | D17: =IFERROR((C17/C18)-1,0) -> -0.0031619083 | F17: 46215 | G17: 24334.3 | H17: =IFERROR((G17/G18)-1,0) -> 0.0052629622
B18: 46208 | C18: 2150.6 | D18: =IFERROR((C18/C19)-1,0) -> -0.022987461 | F18: 46208 | G18: 24206.9 | H18: =IFERROR((G18/G19)-1,0) -> -0.002634848
B19: 46201 | C19: 2201.2 | D19: =IFERROR((C19/C20)-1,0) -> 0.012418361 | F19: 46201 | G19: 24270.85 | H19: =IFERROR((G19/G20)-1,0) -> 0.0089312438
B20: 46194 | C20: 2174.2 | D20: =IFERROR((C20/C21)-1,0) -> -0.0092955436 | F20: 46194 | G20: 24056 | H20: =IFERROR((G20/G21)-1,0) -> 0.0017865249
B21: 46187 | C21: 2194.6 | D21: =IFERROR((C21/C22)-1,0) -> 0.011895979 | F21: 46187 | G21: 24013.1 | H21: =IFERROR((G21/G22)-1,0) -> 0.01651787
B22: 46180 | C22: 2168.8 | D22: =IFERROR((C22/C23)-1,0) -> 0.022295546 | F22: 46180 | G22: 23622.9 | H22: =IFERROR((G22/G23)-1,0) -> 0.010964321
... B524: 42666 | C524: 836.5 | D524: =IFERROR((C524/C525)-1,0) -> -0.017269737 | F524: 42666 | G524: 8638 | H524: =IFERROR((G524/G525)-1,0) -> -0.006332645
B525: 42659 | C525: 851.2 | D525: 0 | F525: 42659 | G525: 8693.05 | H525: 0

Sheet COMP Analysis
B2: ="COMP Analysis for "&'Data Sheet'!B1 -> COMP Analysis for HINDUSTAN UNILEVER LTD
C3: Market Data | I3: Financial Data | N3: Valuation
B4: Company | C4: Share Price | D4: Share Outstanding | E4: Market Cap | F4: Net Debt | G4: Enterprise Value | I4: Revenue | J4: EBITDA | K4: EBIT | L4: Net Income | N4: EV/Revenue | O4: EV/EBITDA | P4: EV/EBIT | Q4: P/E
B5: Hind. Unilever | C5: 1873.3 | D5: =E5/C5 -> 234.95911 | E5: 440148.9 | F5: ='Historical Financial Statement'!L41-'Historical Financial Statement'!L58 -> -1505 | G5: =SUM(E5,F5) -> 438643.9 | I5: 61975 | J5: ='Historical Financial Statement'!L13 -> 14464 | K5: ='Historical Financial Statement'!L17 -> 13278 | L5: ='Historical Financial Statement'!L26 -> 15427 | N5: =G5/I5 -> 7.0777555 | O5: =G5/J5 -> 30.326597 | P5: =G5/K5 -> 33.035389 | Q5: =E5/L5 -> 28.531075
B6: ITC | C6: 259.8 | D6: =E6/C6 -> 1253.0517 | E6: 325542.83 | F6: =2162-2136 -> 26 | G6: =SUM(E6,F6) -> 325568.83 | I6: 71984 | J6: 25196 | K6: 23722 | L6: 20286 | N6: =G6/I6 -> 4.5227944 | O6: =G6/J6 -> 12.921449 | P6: =G6/K6 -> 13.724342 | Q6: =E6/L6 -> 16.04766
B7: Hindustan Foods | C7: 575.35 | D7: =E7/C7 -> 12.130929 | E7: 6979.53 | F7: =571-29 -> 542 | G7: =SUM(E7,F7) -> 7521.53 | I7: 3276 | J7: 244 | K7: 301.58 | L7: 119 | N7: =G7/I7 -> 2.2959493 | O7: =G7/J7 -> 30.825943 | P7: =G7/K7 -> 24.940414 | Q7: =E7/L7 -> 58.651513
B8: Godavari Bioref. | C8: 221.7 | D8: =E8/C8 -> 5.1175462 | E8: 1134.56 | F8: =525-19 -> 506 | G8: =SUM(E8,F8) -> 1640.56 | I8: 1965 | J8: 125 | K8: 79.93 | L8: 1 | N8: =G8/I8 -> 0.83489059 | O8: =G8/J8 -> 13.12448 | P8: =G8/K8 -> 20.524959 | Q8: =E8/L8 -> 1134.56
B9: Davangere Sugar | C9: 2.26 | D9: =E9/C9 -> 169.58407 | E9: 383.26 | F9: =250-7 -> 243 | G9: =SUM(E9,F9) -> 626.26 | I9: 239 | J9: 48 | K9: 38.03 | L9: 9 | N9: =G9/I9 -> 2.6203347 | O9: =G9/J9 -> 13.047083 | P9: =G9/K9 -> 16.467526 | Q9: =E9/L9 -> 42.584444
B11: Max | N11: =MAX(N5:N9) -> 7.0777555 | O11: =MAX(O5:O9) -> 30.825943 | P11: =MAX(P5:P9) -> 33.035389 | Q11: =MAX(Q5:Q9) -> 1134.56
B12: 3rd Quartile | N12: =_xlfn.PERCENTILE.EXC(N5:N9,0.75) -> 5.800275 | O12: =_xlfn.PERCENTILE.EXC(O5:O9,0.75) -> 30.57627 | P12: =_xlfn.PERCENTILE.EXC(P5:P9,0.75) -> 28.987902 | Q12: =_xlfn.PERCENTILE.EXC(Q5:Q9,0.75) -> 596.60576
B13: Median | N13: =MEDIAN(N5:N9) -> 2.6203347 | O13: =MEDIAN(O5:O9) -> 13.12448 | P13: =MEDIAN(P5:P9) -> 20.524959 | Q13: =MEDIAN(Q5:Q9) -> 42.584444
B14: Average | N14: =AVERAGE(N5:N9) -> 3.4703449 | O14: =AVERAGE(O5:O9) -> 20.04911 | P14: =AVERAGE(P5:P9) -> 21.738526 | Q14: =AVERAGE(Q5:Q9) -> 256.07494
B15: 1st Quartile | N15: =_xlfn.PERCENTILE.EXC(N5:N9,0.25) -> 1.56542 | O15: =_xlfn.PERCENTILE.EXC(O5:O9,0.25) -> 12.984266 | P15: =_xlfn.PERCENTILE.EXC(P5:P9,0.25) -> 15.095934 | Q15: =_xlfn.PERCENTILE.EXC(Q5:Q9,0.25) -> 22.289368
B16: Min | N16: =MIN(N5:N9) -> 0.83489059 | O16: =MIN(O5:O9) -> 12.921449 | P16: =MIN(P5:P9) -> 13.724342 | Q16: =MIN(Q5:Q9) -> 16.04766
N18: Valuation
B19: ='Data Sheet'!B1 -> HINDUSTAN UNILEVER LTD | N19: EV/Revenue | O19: EV/EBITDA | P19: EV/EBIT | Q19: P/E
B20: Implied Enterprise Value | N20: =I5*N13 -> 162395.24 | O20: =J5*O13 -> 189832.48 | P20: =K5*P13 -> 272530.41 | Q20: =L5*Q13 -> 656950.22
B21: Net Debt | N21: =$F5 -> -1505 | O21: =$F5 -> -1505 | P21: =$F5 -> -1505 | Q21: =$F5 -> -1505
B22: Implied Market Value | N22: =N20-N21 -> 163900.24 | O22: =O20-O21 -> 191337.48 | P22: =P20-P21 -> 274035.41 | Q22: =Q20-Q21 -> 658455.22
B23: Shares Outstanding | N23: =$D5 -> 234.95911 | O23: =$D5 -> 234.95911 | P23: =$D5 -> 234.95911 | Q23: =$D5 -> 234.95911
B24: Implied Value Per Share | N24: =N22/N23 -> 697.56923 | O24: =O22/O23 -> 814.34373 | P24: =P22/P23 -> 1166.3111 | Q24: =Q22/Q23 -> 2802.4248

Sheet DuPont Model
B1: ="Dupont Model for "&'Data Sheet'!B1 -> Dupont Model for HINDUSTAN UNILEVER LTD
B2: ='Historical Financial Statement'!B2 -> Report Date | C2: ='Historical Financial Statement'!C2 -> 42825 | D2: ='Historical Financial Statement'!D2 -> 43190 | E2: ='Historical Financial Statement'!E2 -> 43555 | F2: ='Historical Financial Statement'!F2 -> 43921 | G2: ='Historical Financial Statement'!G2 -> 44286 | H2: ='Historical Financial Statement'!H2 -> 44651 | I2: ='Historical Financial Statement'!I2 -> 45016 | ... Q2: ='Historical Financial Statement'!Q2 -> 47937
B3: Tax Burden | C3: ='Historical Financial Statement'!C26/'Historical Financial Statement'!C22 -> 0.70200125 | D3: ='Historical Financial Statement'!D26/'Historical Financial Statement'!D22 -> 0.7188744 | E3: ='Historical Financial Statement'!E26/'Historical Financial Statement'!E22 -> 0.70828444 | F3: ='Historical Financial Statement'!F26/'Historical Financial Statement'!F22 -> 0.74109107 | G3: ='Historical Financial Statement'!G26/'Historical Financial Statement'!G22 -> 0.75824595 | H3: ='Historical Financial Statement'!H26/'Historical Financial Statement'!H22 -> 0.75117131 | I3: ='Historical Financial Statement'!I26/'Historical Financial Statement'!I22 -> 0.76167903 | J3: ='Historical Financial Statement'!J26/'Historical Financial Statement'!J22 -> 0.73959781 | ... Q3: ='Historical Financial Statement'!Q26/'Historical Financial Statement'!Q22 -> 0.77635156
B4: Interest Burden | C4: ='Historical Financial Statement'!C22/'Historical Financial Statement'!C17 -> 1.1318351 | D4: ='Historical Financial Statement'!D22/'Historical Financial Statement'!D17 -> 1.0716387 | E4: ='Historical Financial Statement'!E22/'Historical Financial Statement'!E17 -> 1.0504129 | F4: ='Historical Financial Statement'!F22/'Historical Financial Statement'!F17 -> 1.0496421 | G4: ='Historical Financial Statement'!G22/'Historical Financial Statement'!G17 -> 1.0172614 | H4: ='Historical Financial Statement'!H22/'Historical Financial Statement'!H17 -> 1.0227392 | I4: ='Historical Financial Statement'!I22/'Historical Financial Statement'!I17 -> 1.0378511 | J4: ='Historical Financial Statement'!J22/'Historical Financial Statement'!J17 -> 1.0444512 | ... Q4: ='Historical Financial Statement'!Q22/'Historical Financial Statement'!Q17 -> 1.1630053
B5: Operating Margin | C5: ='Historical Financial Statement'!C18 -> 0.17720288 | D5: ='Historical Financial Statement'!D18 -> 0.1969008 | E5: ='Historical Financial Statement'!E18 -> 0.21224885 | F5: ='Historical Financial Statement'!F18 -> 0.22333376 | G5: ='Historical Financial Statement'!G18 -> 0.22419341 | H5: ='Historical Financial Statement'!H18 -> 0.22421034 | I5: ='Historical Financial Statement'!I18 -> 0.21307318 | J5: ='Historical Financial Statement'!J18 -> 0.21652417 | ... Q5: ='Historical Financial Statement'!Q18 -> 0.22672268
B6: Net Profit Margin | C6: ='Historical Financial Statement'!C27 -> 0.14079649 | D6: ='Historical Financial Statement'!D27 -> 0.15168718 | E6: ='Historical Financial Statement'!E27 -> 0.15791126 | F6: ='Historical Financial Statement'!F27 -> 0.17372696 | G6: ='Historical Financial Statement'!G27 -> 0.17292808 | H6: ='Historical Financial Statement'!H27 -> 0.17225011 | I6: ='Historical Financial Statement'!I27 -> 0.16843636 | J6: ='Historical Financial Statement'!J27 -> 0.16725926 | ... Q6: ='Historical Financial Statement'!Q27 -> 0.20470813
B7: Assets Turnover Ratio | C7: ='Historical Financial Statement'!C5/'Historical Financial Statement'!C61 -> 2.1618873 | D7: ='Historical Financial Statement'!D5/'Historical Financial Statement'!D61 -> 2.0132369 | E7: ='Historical Financial Statement'!E5/'Historical Financial Statement'!E61 -> 2.1396026 | F7: ='Historical Financial Statement'!F5/'Historical Financial Statement'!F61 -> 1.9786246 | G7: ='Historical Financial Statement'!G5/'Historical Financial Statement'!G61 -> 0.67525985 | H7: ='Historical Financial Statement'!H5/'Historical Financial Statement'!H61 -> 0.73408664 | I7: ='Historical Financial Statement'!I5/'Historical Financial Statement'!I61 -> 0.82344588 | J7: ='Historical Financial Statement'!J5/'Historical Financial Statement'!J61 -> 0.78453734 | ... Q7: ='Historical Financial Statement'!Q5/'Historical Financial Statement'!Q61 -> 1.0889464
B8: Equity Multiplier | C8: ='Historical Financial Statement'!C61/SUM('Historical Financial Statement'!C31:C32) -> 2.2728814 | D8: ='Historical Financial Statement'!D61/SUM('Historical Financial Statement'!D31:D32) -> 2.4238869 | E8: ='Historical Financial Statement'!E61/SUM('Historical Financial Statement'!E31:E32) -> 2.3325499 | F8: ='Historical Financial Statement'!F61/SUM('Historical Financial Statement'!F31:F32) -> 2.4407919 | G8: ='Historical Financial Statement'!G61/SUM('Historical Financial Statement'!G31:G32) -> 1.4360164 | H8: ='Historical Financial Statement'!H61/SUM('Historical Financial Statement'!H31:H32) -> 1.4302092 | I8: ='Historical Financial Statement'!I61/SUM('Historical Financial Statement'!I31:I32) -> 1.4301786 | J8: ='Historical Financial Statement'!J61/SUM('Historical Financial Statement'!J31:J32) -> 1.5120946 | ... Q8: ='Historical Financial Statement'!Q61/SUM('Historical Financial Statement'!Q31:Q32) -> 1.3406853
B12: DuPont 3 Step Model
B13: =B2 -> Report Date | C13: =C2 -> 42825 | D13: =D2 -> 43190 | E13: =E2 -> 43555 | F13: =F2 -> 43921 | G13: =G2 -> 44286 | H13: =H2 -> 44651 | I13: =I2 -> 45016 | ... Q13: =Q2 -> 47937
B14: Rerurn On Equity | C14: =C6*C7*C8 -> 0.69183359 | D14: =D6*D7*D8 -> 0.74021201 | E14: =E6*E7*E8 -> 0.78809244 | F14: =F6*F7*F8 -> 0.83899888 | G14: =G6*G7*G8 -> 0.16768563 | H14: =H6*H7*H8 -> 0.18084495 | I14: =I6*I7*I8 -> 0.19836323 | J14: =J6*J7*J8 -> 0.19841877 | ... Q14: =Q6*Q7*Q8 -> 0.29886044
B18: DuPont 5 Step Model
B19: =B2 -> Report Date | C19: =C2 -> 42825 | D19: =D2 -> 43190 | E19: =E2 -> 43555 | F19: =F2 -> 43921 | G19: =G2 -> 44286 | H19: =H2 -> 44651 | I19: =I2 -> 45016 | ... Q19: =Q2 -> 47937
B20: Return On Equity | C20: =C3*C4*C5*C7*C8 -> 0.69183359 | D20: =D3*D4*D5*D7*D8 -> 0.74021201 | E20: =E3*E4*E5*E7*E8 -> 0.78809244 | F20: =F3*F4*F5*F7*F8 -> 0.83899888 | G20: =G3*G4*G5*G7*G8 -> 0.16768563 | H20: =H3*H4*H5*H7*H8 -> 0.18084495 | I20: =I3*I4*I5*I7*I8 -> 0.19836323 | J20: =J3*J4*J5*J7*J8 -> 0.19841877 | ... Q20: =Q3*Q4*Q5*Q7*Q8 -> 0.29886044

Sheet Common Size Statement
B1: ="Common Size Income Statement for "&'Data Sheet'!B1 -> Common Size Income Statement for HINDUSTAN UNILEVER LTD
B2: ='Data Sheet'!A16 -> Report Date | C2: ='Data Sheet'!B16 -> 42825 | D2: ='Data Sheet'!C16 -> 43190 | E2: ='Data Sheet'!D16 -> 43555 | F2: ='Data Sheet'!E16 -> 43921 | G2: ='Data Sheet'!F16 -> 44286 | H2: ='Data Sheet'!G16 -> 44651 | I2: ='Data Sheet'!H16 -> 45016 | ... L2: ='Data Sheet'!K16 -> 46112
B3: ='Data Sheet'!A17 -> Sales | C3: ='Data Sheet'!B17/'Data Sheet'!B$17 -> 1 | D3: ='Data Sheet'!C17/'Data Sheet'!C$17 -> 1 | E3: ='Data Sheet'!D17/'Data Sheet'!D$17 -> 1 | F3: ='Data Sheet'!E17/'Data Sheet'!E$17 -> 1 | G3: ='Data Sheet'!F17/'Data Sheet'!F$17 -> 1 | H3: ='Data Sheet'!G17/'Data Sheet'!G$17 -> 1 | I3: ='Data Sheet'!H17/'Data Sheet'!H$17 -> 1 | J3: ='Data Sheet'!I17/'Data Sheet'!I$17 -> 1 | ... L3: ='Data Sheet'!K17/'Data Sheet'!K$17 -> 1
B4: ='Data Sheet'!A18 -> Raw Material Cost | C4: ='Data Sheet'!B18/'Data Sheet'!B$17 -> 0.41282534 | D4: ='Data Sheet'!C18/'Data Sheet'!C$17 -> 0.40141926 | E4: ='Data Sheet'!D18/'Data Sheet'!D$17 -> 0.40367308 | F4: ='Data Sheet'!E18/'Data Sheet'!E$17 -> 0.39649349 | G4: ='Data Sheet'!F18/'Data Sheet'!F$17 -> 0.43012436 | H4: ='Data Sheet'!G18/'Data Sheet'!G$17 -> 0.43752075 | I4: ='Data Sheet'!H18/'Data Sheet'!H$17 -> 0.47413093 | J4: ='Data Sheet'!I18/'Data Sheet'!I$17 -> 0.43986175 | ... L4: ='Data Sheet'!K18/'Data Sheet'!K$17 -> 0.46604276
B5: ='Data Sheet'!A19 -> Change in Inventory | C5: ='Data Sheet'!B19/'Data Sheet'!B$17 -> -0.0048918156 | D5: ='Data Sheet'!C19/'Data Sheet'!C$17 -> 0.0020564808 | E5: ='Data Sheet'!D19/'Data Sheet'!D$17 -> -0.00031393889 | F5: ='Data Sheet'!E19/'Data Sheet'!E$17 -> 0.0031197628 | G5: ='Data Sheet'!F19/'Data Sheet'!F$17 -> 0.0085007392 | H5: ='Data Sheet'!G19/'Data Sheet'!G$17 -> 0.00037114449 | I5: ='Data Sheet'!H19/'Data Sheet'!H$17 -> 0.00089611795 | J5: ='Data Sheet'!I19/'Data Sheet'!I$17 -> 0.00013229919 | ... L5: ='Data Sheet'!K19/'Data Sheet'!K$17 -> 0.0063735377
B6: ='Data Sheet'!A20 -> Power and Fuel | C6: ='Data Sheet'!B20/'Data Sheet'!B$17 -> 0.0080589526 | D6: ='Data Sheet'!C20/'Data Sheet'!C$17 -> 0.0075018103 | E6: ='Data Sheet'!D20/'Data Sheet'!D$17 -> 0.0070374634 | F6: ='Data Sheet'!E20/'Data Sheet'!E$17 -> 0.006780972 | G6: ='Data Sheet'!F20/'Data Sheet'!F$17 -> 0.0066092704 | H6: ='Data Sheet'!G20/'Data Sheet'!G$17 -> 0.005410896 | I6: ='Data Sheet'!H20/'Data Sheet'!H$17 -> 0.0054950629 | J6: ='Data Sheet'!I20/'Data Sheet'!I$17 -> 0.0063503613 | ... L6: ='Data Sheet'!K20/'Data Sheet'!K$17 -> 0.005873336
B7: ='Data Sheet'!A21 -> Other Mfr. Exp | C7: ='Data Sheet'!B21/'Data Sheet'!B$17 -> 0.086892443 | D7: ='Data Sheet'!C21/'Data Sheet'!C$17 -> 0.085677046 | E7: ='Data Sheet'!D21/'Data Sheet'!D$17 -> 0.07895563 | F7: ='Data Sheet'!E21/'Data Sheet'!E$17 -> 0.073739848 | G7: ='Data Sheet'!F21/'Data Sheet'!F$17 -> 0.061896687 | H7: ='Data Sheet'!G21/'Data Sheet'!G$17 -> 0.065028422 | I7: ='Data Sheet'!H21/'Data Sheet'!H$17 -> 0.062643717 | J7: ='Data Sheet'!I21/'Data Sheet'!I$17 -> 0.054457656 | ... L7: ='Data Sheet'!K21/'Data Sheet'!K$17 -> 0.049681323
B8: ='Data Sheet'!A22 -> Employee Cost | C8: ='Data Sheet'!B22/'Data Sheet'!B$17 -> 0.050799624 | D8: ='Data Sheet'!C22/'Data Sheet'!C$17 -> 0.050543085 | E8: ='Data Sheet'!D22/'Data Sheet'!D$17 -> 0.04570427 | F8: ='Data Sheet'!E22/'Data Sheet'!E$17 -> 0.04359933 | G8: ='Data Sheet'!F22/'Data Sheet'!F$17 -> 0.048460736 | H8: ='Data Sheet'!G22/'Data Sheet'!G$17 -> 0.046861876 | I8: ='Data Sheet'!H22/'Data Sheet'!H$17 -> 0.045059516 | J8: ='Data Sheet'!I22/'Data Sheet'!I$17 -> 0.046007045 | ... L8: ='Data Sheet'!K22/'Data Sheet'!K$17 -> 0.045873336
B9: ='Data Sheet'!A23 -> Selling and admin | C9: ='Data Sheet'!B23/'Data Sheet'!B$17 -> 0.20407651 | D9: ='Data Sheet'!C23/'Data Sheet'!C$17 -> 0.2057929 | E9: ='Data Sheet'!D23/'Data Sheet'!D$17 -> 0.20000523 | F9: ='Data Sheet'!E23/'Data Sheet'!E$17 -> 0.19396674 | G9: ='Data Sheet'!F23/'Data Sheet'!F$17 -> 0.16921037 | H9: ='Data Sheet'!G23/'Data Sheet'!G$17 -> 0.15716993 | I9: ='Data Sheet'!H23/'Data Sheet'!H$17 -> 0.146659 | J9: ='Data Sheet'!I23/'Data Sheet'!I$17 -> 0.17466801 | ... L9: ='Data Sheet'!K23/'Data Sheet'!K$17 -> 0.16077451
B10: ='Data Sheet'!A24 -> Other Expenses | C10: ='Data Sheet'!B24/'Data Sheet'!B$17 -> 0.042834744 | D10: ='Data Sheet'!C24/'Data Sheet'!C$17 -> 0.040376539 | E10: ='Data Sheet'!D24/'Data Sheet'!D$17 -> 0.038352867 | F10: ='Data Sheet'!E24/'Data Sheet'!E$17 -> 0.041021013 | G10: ='Data Sheet'!F24/'Data Sheet'!F$17 -> 0.046004 | H10: ='Data Sheet'!G24/'Data Sheet'!G$17 -> 0.044146661 | I10: ='Data Sheet'!H24/'Data Sheet'!H$17 -> 0.036419586 | J10: ='Data Sheet'!I24/'Data Sheet'!I$17 -> 0.044121781 | ... L10: ='Data Sheet'!K24/'Data Sheet'!K$17 -> 0.044743848
B11: ='Data Sheet'!A25 -> Other Income | C11: ='Data Sheet'!B25/'Data Sheet'!B$17 -> 0.024051427 | D11: ='Data Sheet'!C25/'Data Sheet'!C$17 -> 0.014685011 | E11: ='Data Sheet'!D25/'Data Sheet'!D$17 -> 0.011432608 | F11: ='Data Sheet'!E25/'Data Sheet'!E$17 -> 0.013819776 | G11: ='Data Sheet'!F25/'Data Sheet'!F$17 -> 0.006217932 | H11: ='Data Sheet'!G25/'Data Sheet'!G$17 -> 0.0070126775 | I11: ='Data Sheet'!H25/'Data Sheet'!H$17 -> 0.009772758 | J11: ='Data Sheet'!I25/'Data Sheet'!I$17 -> 0.014619061 | ... L11: ='Data Sheet'!K25/'Data Sheet'!K$17 -> 0.089907221
B12: ='Data Sheet'!A26 -> Depreciation | C12: ='Data Sheet'!B26/'Data Sheet'!B$17 -> 0.012417686 | D12: ='Data Sheet'!C26/'Data Sheet'!C$17 -> 0.01384504 | E12: ='Data Sheet'!D26/'Data Sheet'!D$17 -> 0.013708665 | F12: ='Data Sheet'!E26/'Data Sheet'!E$17 -> 0.024184607 | G12: ='Data Sheet'!F26/'Data Sheet'!F$17 -> 0.022001913 | H12: ='Data Sheet'!G26/'Data Sheet'!G$17 -> 0.020022269 | I12: ='Data Sheet'!H26/'Data Sheet'!H$17 -> 0.017415122 | J12: ='Data Sheet'!I26/'Data Sheet'!I$17 -> 0.018141527 | ... L12: ='Data Sheet'!K26/'Data Sheet'!K$17 -> 0.019136749
B13: ='Data Sheet'!A27 -> Interest | C13: ='Data Sheet'!B27/'Data Sheet'!B$17 -> 0.00068987143 | D13: ='Data Sheet'!C27/'Data Sheet'!C$17 -> 0.00057929037 | E13: ='Data Sheet'!D27/'Data Sheet'!D$17 -> 0.00073252407 | F13: ='Data Sheet'!E27/'Data Sheet'!E$17 -> 0.0027330153 | G13: ='Data Sheet'!F27/'Data Sheet'!F$17 -> 0.0023480303 | H13: ='Data Sheet'!G27/'Data Sheet'!G$17 -> 0.0019143242 | I13: ='Data Sheet'!H27/'Data Sheet'!H$17 -> 0.0017076965 | J13: ='Data Sheet'!I27/'Data Sheet'!I$17 -> 0.0049942946 | ... L13: ='Data Sheet'!K27/'Data Sheet'!K$17 -> 0.0058572005
B14: ='Data Sheet'!A28 -> Profit before tax | C14: ='Data Sheet'!B28/'Data Sheet'!B$17 -> 0.20056444 | D14: ='Data Sheet'!C28/'Data Sheet'!C$17 -> 0.21100652 | E14: ='Data Sheet'!D28/'Data Sheet'!D$17 -> 0.22294893 | F14: ='Data Sheet'!E28/'Data Sheet'!E$17 -> 0.23442052 | G14: ='Data Sheet'!F28/'Data Sheet'!F$17 -> 0.22806331 | H14: ='Data Sheet'!G28/'Data Sheet'!G$17 -> 0.22930869 | I14: ='Data Sheet'!H28/'Data Sheet'!H$17 -> 0.22113824 | J14: ='Data Sheet'!I28/'Data Sheet'!I$17 -> 0.22614894 | ... L14: ='Data Sheet'!K28/'Data Sheet'!K$17 -> 0.2982977
... B19: ='Data Sheet'!A33 -> EBIT | C19: ='Data Sheet'!B33/'Data Sheet'!B$17 -> 0.20125431 | D19: ='Data Sheet'!C33/'Data Sheet'!C$17 -> 0.21158581 | E19: ='Data Sheet'!D33/'Data Sheet'!D$17 -> 0.22368146 | F19: ='Data Sheet'!E33/'Data Sheet'!E$17 -> 0.23715354 | G19: ='Data Sheet'!F33/'Data Sheet'!F$17 -> 0.23041134 | H19: ='Data Sheet'!G33/'Data Sheet'!G$17 -> 0.23122302 | I19: ='Data Sheet'!H33/'Data Sheet'!H$17 -> 0.22284594 | J19: ='Data Sheet'!I33/'Data Sheet'!I$17 -> 0.23114323 | ... L19: ='Data Sheet'!K33/'Data Sheet'!K$17 -> 0.3041549
B22: ="Common Size Balance Sheet for "&'Data Sheet'!B1 -> Common Size Balance Sheet for HINDUSTAN UNILEVER LTD
B23: ='Historical Financial Statement'!B2 -> Report Date | C23: ='Historical Financial Statement'!C2 -> 42825 | D23: ='Historical Financial Statement'!D2 -> 43190 | E23: ='Historical Financial Statement'!E2 -> 43555 | F23: ='Historical Financial Statement'!F2 -> 43921 | G23: ='Historical Financial Statement'!G2 -> 44286 | H23: ='Historical Financial Statement'!H2 -> 44651 | I23: ='Historical Financial Statement'!I2 -> 45016 | ... L23: ='Historical Financial Statement'!L2 -> 46112
B24: ='Data Sheet'!A57 -> Equity Share Capital | C24: ='Data Sheet'!B57/'Data Sheet'!B$61 -> 0.014643075 | D24: ='Data Sheet'!C57/'Data Sheet'!C$61 -> 0.012595487 | E24: ='Data Sheet'!D57/'Data Sheet'!D$61 -> 0.01209068 | F24: ='Data Sheet'!E57/'Data Sheet'!E$61 -> 0.011019284 | G24: ='Data Sheet'!F57/'Data Sheet'!F$61 -> 0.0034499971 | H24: ='Data Sheet'!G57/'Data Sheet'!G$61 -> 0.0033698037 | I24: ='Data Sheet'!H57/'Data Sheet'!H$61 -> 0.0032718413 | J24: ='Data Sheet'!I57/'Data Sheet'!I$61 -> 0.0030489387 | ... L24: ='Data Sheet'!K57/'Data Sheet'!K$61 -> 0.0030135159
B25: ='Data Sheet'!A58 -> Reserves | C25: ='Data Sheet'!B58/'Data Sheet'!B$61 -> 0.4253271 | D25: ='Data Sheet'!C58/'Data Sheet'!C$61 -> 0.39996501 | E25: ='Data Sheet'!D58/'Data Sheet'!D$61 -> 0.41662469 | F25: ='Data Sheet'!E58/'Data Sheet'!E$61 -> 0.39868381 | G25: ='Data Sheet'!F58/'Data Sheet'!F$61 -> 0.6929209 | H25: ='Data Sheet'!G58/'Data Sheet'!G$61 -> 0.69582861 | I25: ='Data Sheet'!H58/'Data Sheet'!H$61 -> 0.69594152 | J25: ='Data Sheet'!I58/'Data Sheet'!I$61 -> 0.65828533 | ... L25: ='Data Sheet'!K58/'Data Sheet'!K$61 -> 0.62819625
B26: ='Data Sheet'!A59 -> Borrowings | C26: ='Data Sheet'!B59/'Data Sheet'!B$61 -> 0 | D26: ='Data Sheet'!C59/'Data Sheet'!C$61 -> 0 | E26: ='Data Sheet'!D59/'Data Sheet'!D$61 -> 0 | F26: ='Data Sheet'!E59/'Data Sheet'!E$61 -> 0 | G26: ='Data Sheet'!F59/'Data Sheet'!F$61 -> 0.013844031 | H26: ='Data Sheet'!G59/'Data Sheet'!G$61 -> 0.013923742 | I26: ='Data Sheet'!H59/'Data Sheet'!H$61 -> 0.014465715 | J26: ='Data Sheet'!I59/'Data Sheet'!I$61 -> 0.017826561 | ... L26: ='Data Sheet'!K59/'Data Sheet'!K$61 -> 0.016991101
B27: ='Data Sheet'!A60 -> Other Liabilities | C27: ='Data Sheet'!B60/'Data Sheet'!B$61 -> 0.56002983 | D27: ='Data Sheet'!C60/'Data Sheet'!C$61 -> 0.5874395 | E27: ='Data Sheet'!D60/'Data Sheet'!D$61 -> 0.57128463 | F27: ='Data Sheet'!E60/'Data Sheet'!E$61 -> 0.59029691 | G27: ='Data Sheet'!F60/'Data Sheet'!F$61 -> 0.28978507 | H27: ='Data Sheet'!G60/'Data Sheet'!G$61 -> 0.28687784 | I27: ='Data Sheet'!H60/'Data Sheet'!H$61 -> 0.28632092 | J27: ='Data Sheet'!I60/'Data Sheet'!I$61 -> 0.32083917 | ... L27: ='Data Sheet'!K60/'Data Sheet'!K$61 -> 0.35179913
B29: ='Data Sheet'!A61&" Liabilities" -> Total Liabilities | C29: ='Data Sheet'!B61/'Data Sheet'!B$61 -> 1 | D29: ='Data Sheet'!C61/'Data Sheet'!C$61 -> 1 | E29: ='Data Sheet'!D61/'Data Sheet'!D$61 -> 1 | F29: ='Data Sheet'!E61/'Data Sheet'!E$61 -> 1 | G29: ='Data Sheet'!F61/'Data Sheet'!F$61 -> 1 | H29: ='Data Sheet'!G61/'Data Sheet'!G$61 -> 1 | I29: ='Data Sheet'!H61/'Data Sheet'!H$61 -> 1 | J29: ='Data Sheet'!I61/'Data Sheet'!I$61 -> 1 | ... L29: ='Data Sheet'!K61/'Data Sheet'!K$61 -> 1
B31: ='Data Sheet'!A62 -> Net Block | C31: ='Data Sheet'!B62/'Data Sheet'!B$66 -> 0.27279506 | D31: ='Data Sheet'!C62/'Data Sheet'!C$66 -> 0.24153012 | E31: ='Data Sheet'!D62/'Data Sheet'!D$66 -> 0.24310104 | F31: ='Data Sheet'!E62/'Data Sheet'!E$66 -> 0.25793286 | G31: ='Data Sheet'!F62/'Data Sheet'!F$66 -> 0.74911915 | H31: ='Data Sheet'!G62/'Data Sheet'!G$66 -> 0.73180664 | I31: ='Data Sheet'!H62/'Data Sheet'!H$66 -> 0.71569788 | J31: ='Data Sheet'!I62/'Data Sheet'!I$66 -> 0.679576 | ... L31: ='Data Sheet'!K62/'Data Sheet'!K$66 -> 0.67219358
B32: ='Data Sheet'!A63 -> Capital Work in Progress | C32: ='Data Sheet'!B63/'Data Sheet'!B$66 -> 0.013761779 | D32: ='Data Sheet'!C63/'Data Sheet'!C$66 -> 0.025074348 | E32: ='Data Sheet'!D63/'Data Sheet'!D$66 -> 0.020878813 | F32: ='Data Sheet'!E63/'Data Sheet'!E$66 -> 0.026170799 | G32: ='Data Sheet'!F63/'Data Sheet'!F$66 -> 0.0091461624 | H32: ='Data Sheet'!G63/'Data Sheet'!G$66 -> 0.012919971 | I32: ='Data Sheet'!H63/'Data Sheet'!H$66 -> 0.014201183 | J32: ='Data Sheet'!I63/'Data Sheet'!I$66 -> 0.0118714 | ... L32: ='Data Sheet'!K63/'Data Sheet'!K$66 -> 0.010681952
B33: ='Data Sheet'!A64 -> Investments | C33: ='Data Sheet'!B64/'Data Sheet'!B$66 -> 0.25618602 | D33: ='Data Sheet'!C64/'Data Sheet'!C$66 -> 0.18140999 | E33: ='Data Sheet'!D64/'Data Sheet'!D$66 -> 0.16507137 | F33: ='Data Sheet'!E64/'Data Sheet'!E$66 -> 0.076522804 | G33: ='Data Sheet'!F64/'Data Sheet'!F$66 -> 0.043969112 | H33: ='Data Sheet'!G64/'Data Sheet'!G$66 -> 0.059107791 | I33: ='Data Sheet'!H64/'Data Sheet'!H$66 -> 0.052822833 | J33: ='Data Sheet'!I64/'Data Sheet'!I$66 -> 0.071267321 | ... L33: ='Data Sheet'!K64/'Data Sheet'!K$66 -> 0.11385961
B34: ='Data Sheet'!A65 -> Other Assets | C34: ='Data Sheet'!B74/'Data Sheet'!B$66 -> 0.12094095 | D34: ='Data Sheet'!C74/'Data Sheet'!C$66 -> 0.15085428 | E34: ='Data Sheet'!D74/'Data Sheet'!D$66 -> 0.13529247 | F34: ='Data Sheet'!E74/'Data Sheet'!E$66 -> 0.19559229 | G34: ='Data Sheet'!F74/'Data Sheet'!F$66 -> 0.060470374 | H34: ='Data Sheet'!G74/'Data Sheet'!G$66 -> 0.060799862 | I34: ='Data Sheet'!H74/'Data Sheet'!H$66 -> 0.061510616 | J34: ='Data Sheet'!I74/'Data Sheet'!I$66 -> 0.059305101 | ... L34: ='Data Sheet'!K74/'Data Sheet'!K$66 -> 0.071824267
B35: ='Data Sheet'!A67 -> Receivables | C35: ='Data Sheet'!B67/'Data Sheet'!B$66 -> 0.062910989 | D35: ='Data Sheet'!C67/'Data Sheet'!C$66 -> 0.066884366 | E35: ='Data Sheet'!D67/'Data Sheet'!D$66 -> 0.093646795 | F35: ='Data Sheet'!E67/'Data Sheet'!E$66 -> 0.053361902 | G35: ='Data Sheet'!F67/'Data Sheet'!F$66 -> 0.024194022 | H35: ='Data Sheet'!G67/'Data Sheet'!G$66 -> 0.027704088 | I35: ='Data Sheet'!H67/'Data Sheet'!H$66 -> 0.038078663 | J35: ='Data Sheet'!I67/'Data Sheet'!I$66 -> 0.034900618 | ... L35: ='Data Sheet'!K67/'Data Sheet'!K$66 -> 0.038944885
B36: ='Data Sheet'!A68 -> Inventory | C36: ='Data Sheet'!B68/'Data Sheet'!B$66 -> 0.16012474 | D36: ='Data Sheet'!C68/'Data Sheet'!C$66 -> 0.13755904 | E36: ='Data Sheet'!D68/'Data Sheet'!D$66 -> 0.13557235 | F36: ='Data Sheet'!E68/'Data Sheet'!E$66 -> 0.13447607 | G36: ='Data Sheet'!F68/'Data Sheet'!F$66 -> 0.049665277 | H36: ='Data Sheet'!G68/'Data Sheet'!G$66 -> 0.055781006 | I36: ='Data Sheet'!H68/'Data Sheet'!H$66 -> 0.05612252 | J36: ='Data Sheet'!I68/'Data Sheet'!I$66 -> 0.049457678 | ... L36: ='Data Sheet'!K68/'Data Sheet'!K$66 -> 0.056205278
B37: ='Data Sheet'!A69 -> Cash & Bank | C37: ='Data Sheet'!B69/'Data Sheet'!B$66 -> 0.11328046 | D37: ='Data Sheet'!C69/'Data Sheet'!C$66 -> 0.19668785 | E37: ='Data Sheet'!D69/'Data Sheet'!D$66 -> 0.20643717 | F37: ='Data Sheet'!E69/'Data Sheet'!E$66 -> 0.25594327 | G37: ='Data Sheet'!F69/'Data Sheet'!F$66 -> 0.063435903 | H37: ='Data Sheet'!G69/'Data Sheet'!G$66 -> 0.051880637 | I37: ='Data Sheet'!H69/'Data Sheet'!H$66 -> 0.061566307 | J37: ='Data Sheet'!I69/'Data Sheet'!I$66 -> 0.09362188 | ... L37: ='Data Sheet'!K69/'Data Sheet'!K$66 -> 0.036290426
B39: ='Data Sheet'!A66&" Assests" -> Total Assests | C39: ='Data Sheet'!B66/'Data Sheet'!B$66 -> 1 | D39: ='Data Sheet'!C66/'Data Sheet'!C$66 -> 1 | E39: ='Data Sheet'!D66/'Data Sheet'!D$66 -> 1 | F39: ='Data Sheet'!E66/'Data Sheet'!E$66 -> 1 | G39: ='Data Sheet'!F66/'Data Sheet'!F$66 -> 1 | H39: ='Data Sheet'!G66/'Data Sheet'!G$66 -> 1 | I39: ='Data Sheet'!H66/'Data Sheet'!H$66 -> 1 | J39: ='Data Sheet'!I66/'Data Sheet'!I$66 -> 1 | ... L39: ='Data Sheet'!K66/'Data Sheet'!K$66 -> 1

Sheet Manual Data
B1: Cash-Flows
B2: Cash from Operating Activity
B3: Profit from operations | C3: 6219 | D3: 7237 | E3: 8674 | F3: 9473 | G3: 11380 | H3: 12473 | I3: 13557 | J3: 14043 | K3: 14343 | L3: 14538
B4: Receivables | C4: 131 | D4: 0 | E4: 0 | F4: 0 | G4: 0 | H4: 0 | I4: 0 | J4: 0 | K4: 0 | L4: 0
B5: Inventory | C5: 38 | D5: -162 | E5: -195 | F5: -369 | G5: -472 | H5: -737 | I5: -332 | J5: 77 | K5: -540 | L5: -630
B6: Payables | C6: 508 | D6: 0 | E6: 0 | F6: 0 | G6: 0 | H6: 0 | I6: 0 | J6: 0 | K6: 0 | L6: 0
B7: Loans Advances | C7: -46 | D7: 0 | E7: 0 | F7: 0 | G7: 0 | H7: 0 | I7: 0 | J7: 0 | K7: 0 | L7: 0
B8: Other WC items | C8: -93 | D8: 1026 | E8: -66 | F8: 666 | G8: 416 | H8: -52 | I8: -531 | J8: 1059 | K8: -14 | L8: 1314
B9: Working capital changes | C9: =SUM(C4:C8) -> 538 | D9: =SUM(D4:D8) -> 864 | E9: =SUM(E4:E8) -> -261 | F9: =SUM(F4:F8) -> 297 | G9: =SUM(G4:G8) -> -56 | H9: =SUM(H4:H8) -> -789 | I9: =SUM(I4:I8) -> -863 | J9: =SUM(J4:J8) -> 1136 | ... L9: =SUM(L4:L8) -> 684
B10: Direct taxes | C10: -1783 | D10: -2188 | E10: -2685 | F10: -2465 | G10: -2367 | H10: -2720 | I10: -3068 | J10: -295 | K10: -2183 | L10: -4726
B11: Other operating items | C11: -21 | D11: 0 | E11: 0 | F11: 0 | G11: 0 | H11: 0 | I11: 0 | J11: 0 | K11: 0 | L11: 0
B12: Cash-Flow from Operating Activity | C12: =SUM(C3,C9:C11) -> 4953 | D12: =SUM(D3,D9:D11) -> 5913 | E12: =SUM(E3,E9:E11) -> 5728 | F12: =SUM(F3,F9:F11) -> 7305 | G12: =SUM(G3,G9:G11) -> 8957 | H12: =SUM(H3,H9:H11) -> 8964 | I12: =SUM(I3,I9:I11) -> 9626 | J12: =SUM(J3,J9:J11) -> 14884 | ... L12: =SUM(L3,L9:L11) -> 10496
B14: Cash from Investing Activity
B15: Fixed assets purchased | C15: -1024 | D15: -853 | E15: -728 | F15: -765 | G15: -4051 | H15: -919 | I15: -1041 | J15: -1318 | K15: -1149 | L15: -1274
B16: Fixed assets sold | C16: 172 | D16: 26 | E16: 4 | F16: 52 | G16: 97 | H16: 175 | I16: 180 | J16: 20 | K16: 13 | L16: 29
B17: Investments purchased | C17: -26230 | D17: -47755 | E17: -70434 | F17: -34074 | G17: -38450 | H17: -47928 | I17: -22631 | J17: -21198 | K17: -20943 | L17: -23058
B18: Investments sold | C18: 25260 | D18: 48534 | E18: 70761 | F18: 35656 | G18: 37076 | H18: 47173 | I18: 23363 | J18: 19752 | K18: 21984 | L18: 22609
B19: Interest received | C19: 266 | D19: 229 | E19: 308 | F19: 359 | G19: 285 | H19: 171 | I19: 273 | J19: 417 | K19: 768 | L19: 431
B20: Dividends received | C20: 178 | D20: 190 | E20: 103 | F20: 96 | G20: 102 | H20: 131 | I20: 118 | J20: 176 | K20: 169 | L20: 230
B21: Invest in subsidiaries | C21: 0 | D21: 0 | E21: 0 | F21: 0 | G21: -60 | H21: -300 | I21: -264 | J21: 0 | K21: -5 | L21: -3530
B22: Loans to subsidiaries | C22: -84 | D22: -183 | E22: -248 | F22: -292 | G22: -180 | H22: -436 | I22: -493 | J22: -431 | K22: -362 | L22: -171
B23: Redemp n Canc of Shares | C23: 20 | D23: 73 | E23: 0 | F23: 0 | G23: 0 | H23: 0 | I23: 0 | J23: 0 | K23: 0 | L23: 298
B24: Acquisition of companies | C24: 0 | D24: 0 | E24: 0 | F24: 0 | G24: 0 | H24: 0 | I24: 0 | J24: 0 | K24: 0 | L24: 0
B25: Other investing items | C25: 690 | D25: -1522 | E25: -30 | F25: 894 | G25: 4114 | H25: 201 | I25: -567 | J25: -2389 | K25: 6288 | L25: 963
B26: Cash-Flow from Investing Activity | C26: =SUM(C15:C25) -> -752 | D26: =SUM(D15:D25) -> -1261 | E26: =SUM(E15:E25) -> -264 | F26: =SUM(F15:F25) -> 1926 | G26: =SUM(G15:G25) -> -1067 | H26: =SUM(H15:H25) -> -1732 | I26: =SUM(I15:I25) -> -1062 | J26: =SUM(J15:J25) -> -4971 | ... L26: =SUM(L15:L25) -> -3473
B28: Cash from Financing Activity
B29: Proceeds from shares | C29: 0 | D29: 0 | E29: 0 | F29: 0 | G29: 0 | H29: 0 | I29: 0 | J29: 0 | K29: 0 | L29: 0
B30: Interest paid fin | C30: 0 | D30: 0 | E30: -3 | F30: -80 | G30: -86 | H30: -77 | I30: -76 | J30: -98 | K30: -118 | L30: -117
B31: Dividends paid | C31: -3561 | D31: -3896 | E31: -4546 | F31: -5196 | G31: -8811 | H31: -7519 | I31: -8459 | J31: -9398 | K31: -12453 | L31: -10103
B32: Financial liabilities | C32: 0 | D32: 0 | E32: 0 | F32: -352 | G32: -383 | H32: -388 | I32: -431 | J32: -394 | K32: -460 | L32: -464 | M32: =AVERAGE(F32:L32) -> -410.28571
B33: Other financing items | C33: -703 | D33: -755 | E33: -913 | F33: -1048 | G33: 0 | H33: 0 | I33: 0 | J33: 0 | K33: 0 | L33: 0
B34: Cash-Flow from Financing Activity | C34: =SUM(C29:C33) -> -4264 | D34: =SUM(D29:D33) -> -4651 | E34: =SUM(E29:E33) -> -5462 | F34: =SUM(F29:F33) -> -6676 | G34: =SUM(G29:G33) -> -9280 | H34: =SUM(H29:H33) -> -7984 | I34: =SUM(I29:I33) -> -8966 | J34: =SUM(J29:J33) -> -9890 | ... L34: =SUM(L29:L33) -> -10684
B36: Net Cash Flow | C36: =SUM(C34,C26,C12) -> -63 | D36: =SUM(D34,D26,D12) -> 1 | E36: =SUM(E34,E26,E12) -> 2 | F36: =SUM(F34,F26,F12) -> 2555 | G36: =SUM(G34,G26,G12) -> -1390 | H36: =SUM(H34,H26,H12) -> -752 | I36: =SUM(I34,I26,I12) -> -402 | J36: =SUM(J34,J26,J12) -> 23 | ... L36: =SUM(L34,L26,L12) -> -3661
B39: Trade Payables | C39: 6006 | D39: 7013 | E39: 7070 | F39: 7399 | G39: 8627 | H39: 8864 | I39: 9391 | J39: 10148 | K39: 10998 | L39: 12913
B40: Advance from Customers | C40: 70 | D40: 55 | E40: 39 | F40: 154 | G40: 93 | H40: 113 | I40: 86 | J40: 89 | K40: 0 | L40: 0
